{"frames": {

"airport-white.png":
{
	"frame": {"x":287,"y":1,"w":16,"h":20},
	"rotated": false,
	"trimmed": true,
	"spriteSourceSize": {"x":0,"y":12,"w":16,"h":20},
	"sourceSize": {"w":16,"h":32},
	"anchor": {"x":0,"y":0.5}
},
"airport.png":
{
	"frame": {"x":305,"y":1,"w":16,"h":20},
	"rotated": false,
	"trimmed": true,
	"spriteSourceSize": {"x":0,"y":12,"w":16,"h":20},
	"sourceSize": {"w":16,"h":32},
	"anchor": {"x":0,"y":0.5}
},
"beach-0001.png":
{
	"frame": {"x":575,"y":91,"w":13,"h":16},
	"rotated": false,
	"trimmed": true,
	"spriteSourceSize": {"x":0,"y":0,"w":13,"h":16},
	"sourceSize": {"w":16,"h":16},
	"anchor": {"x":0,"y":0}
},
"beach-0010.png":
{
	"frame": {"x":289,"y":114,"w":16,"h":11},
	"rotated": false,
	"trimmed": true,
	"spriteSourceSize": {"x":0,"y":5,"w":16,"h":11},
	"sourceSize": {"w":16,"h":16},
	"anchor": {"x":0,"y":0}
},
"beach-0011.png":
{
	"frame": {"x":161,"y":46,"w":16,"h":16},
	"rotated": false,
	"trimmed": false,
	"spriteSourceSize": {"x":0,"y":0,"w":16,"h":16},
	"sourceSize": {"w":16,"h":16},
	"anchor": {"x":0,"y":0}
},
"beach-0012.png":
{
	"frame": {"x":235,"y":115,"w":16,"h":10},
	"rotated": false,
	"trimmed": true,
	"spriteSourceSize": {"x":0,"y":6,"w":16,"h":10},
	"sourceSize": {"w":16,"h":16},
	"anchor": {"x":0,"y":0}
},
"beach-0021.png":
{
	"frame": {"x":620,"y":91,"w":12,"h":16},
	"rotated": false,
	"trimmed": true,
	"spriteSourceSize": {"x":0,"y":0,"w":12,"h":16},
	"sourceSize": {"w":16,"h":16},
	"anchor": {"x":0,"y":0}
},
"beach-0100.png":
{
	"frame": {"x":792,"y":55,"w":14,"h":16},
	"rotated": false,
	"trimmed": true,
	"spriteSourceSize": {"x":2,"y":0,"w":14,"h":16},
	"sourceSize": {"w":16,"h":16},
	"anchor": {"x":0,"y":0}
},
"beach-0102.png":
{
	"frame": {"x":792,"y":55,"w":14,"h":16},
	"rotated": false,
	"trimmed": true,
	"spriteSourceSize": {"x":2,"y":0,"w":14,"h":16},
	"sourceSize": {"w":16,"h":16},
	"anchor": {"x":0,"y":0}
},
"beach-0110.png":
{
	"frame": {"x":179,"y":45,"w":16,"h":16},
	"rotated": false,
	"trimmed": false,
	"spriteSourceSize": {"x":0,"y":0,"w":16,"h":16},
	"sourceSize": {"w":16,"h":16},
	"anchor": {"x":0,"y":0}
},
"beach-0111.png":
{
	"frame": {"x":197,"y":44,"w":16,"h":16},
	"rotated": false,
	"trimmed": false,
	"spriteSourceSize": {"x":0,"y":0,"w":16,"h":16},
	"sourceSize": {"w":16,"h":16},
	"anchor": {"x":0,"y":0}
},
"beach-0112.png":
{
	"frame": {"x":215,"y":44,"w":16,"h":16},
	"rotated": false,
	"trimmed": false,
	"spriteSourceSize": {"x":0,"y":0,"w":16,"h":16},
	"sourceSize": {"w":16,"h":16},
	"anchor": {"x":0,"y":0}
},
"beach-0120.png":
{
	"frame": {"x":620,"y":109,"w":12,"h":16},
	"rotated": false,
	"trimmed": true,
	"spriteSourceSize": {"x":4,"y":0,"w":12,"h":16},
	"sourceSize": {"w":16,"h":16},
	"anchor": {"x":0,"y":0}
},
"beach-0122.png":
{
	"frame": {"x":620,"y":109,"w":12,"h":16},
	"rotated": false,
	"trimmed": true,
	"spriteSourceSize": {"x":4,"y":0,"w":12,"h":16},
	"sourceSize": {"w":16,"h":16},
	"anchor": {"x":0,"y":0}
},
"beach-0201.png":
{
	"frame": {"x":575,"y":91,"w":13,"h":16},
	"rotated": false,
	"trimmed": true,
	"spriteSourceSize": {"x":0,"y":0,"w":13,"h":16},
	"sourceSize": {"w":16,"h":16},
	"anchor": {"x":0,"y":0}
},
"beach-0210.png":
{
	"frame": {"x":253,"y":115,"w":16,"h":10},
	"rotated": false,
	"trimmed": true,
	"spriteSourceSize": {"x":0,"y":6,"w":16,"h":10},
	"sourceSize": {"w":16,"h":16},
	"anchor": {"x":0,"y":0}
},
"beach-0211.png":
{
	"frame": {"x":233,"y":43,"w":16,"h":16},
	"rotated": false,
	"trimmed": false,
	"spriteSourceSize": {"x":0,"y":0,"w":16,"h":16},
	"sourceSize": {"w":16,"h":16},
	"anchor": {"x":0,"y":0}
},
"beach-0212.png":
{
	"frame": {"x":271,"y":115,"w":16,"h":10},
	"rotated": false,
	"trimmed": true,
	"spriteSourceSize": {"x":0,"y":6,"w":16,"h":10},
	"sourceSize": {"w":16,"h":16},
	"anchor": {"x":0,"y":0}
},
"beach-0221.png":
{
	"frame": {"x":620,"y":91,"w":12,"h":16},
	"rotated": false,
	"trimmed": true,
	"spriteSourceSize": {"x":0,"y":0,"w":12,"h":16},
	"sourceSize": {"w":16,"h":16},
	"anchor": {"x":0,"y":0}
},
"beach-1000.png":
{
	"frame": {"x":55,"y":111,"w":16,"h":14},
	"rotated": false,
	"trimmed": true,
	"spriteSourceSize": {"x":0,"y":0,"w":16,"h":14},
	"sourceSize": {"w":16,"h":16},
	"anchor": {"x":0,"y":0}
},
"beach-1001.png":
{
	"frame": {"x":251,"y":43,"w":16,"h":16},
	"rotated": false,
	"trimmed": false,
	"spriteSourceSize": {"x":0,"y":0,"w":16,"h":16},
	"sourceSize": {"w":16,"h":16},
	"anchor": {"x":0,"y":0}
},
"beach-1002.png":
{
	"frame": {"x":792,"y":73,"w":16,"h":14},
	"rotated": true,
	"trimmed": true,
	"spriteSourceSize": {"x":0,"y":0,"w":16,"h":14},
	"sourceSize": {"w":16,"h":16},
	"anchor": {"x":0,"y":0}
},
"beach-1011.png":
{
	"frame": {"x":269,"y":43,"w":16,"h":16},
	"rotated": false,
	"trimmed": false,
	"spriteSourceSize": {"x":0,"y":0,"w":16,"h":16},
	"sourceSize": {"w":16,"h":16},
	"anchor": {"x":0,"y":0}
},
"beach-1020.png":
{
	"frame": {"x":55,"y":111,"w":16,"h":14},
	"rotated": false,
	"trimmed": true,
	"spriteSourceSize": {"x":0,"y":0,"w":16,"h":14},
	"sourceSize": {"w":16,"h":16},
	"anchor": {"x":0,"y":0}
},
"beach-1021.png":
{
	"frame": {"x":287,"y":42,"w":16,"h":16},
	"rotated": false,
	"trimmed": false,
	"spriteSourceSize": {"x":0,"y":0,"w":16,"h":16},
	"sourceSize": {"w":16,"h":16},
	"anchor": {"x":0,"y":0}
},
"beach-1022.png":
{
	"frame": {"x":792,"y":73,"w":16,"h":14},
	"rotated": true,
	"trimmed": true,
	"spriteSourceSize": {"x":0,"y":0,"w":16,"h":14},
	"sourceSize": {"w":16,"h":16},
	"anchor": {"x":0,"y":0}
},
"beach-1100.png":
{
	"frame": {"x":305,"y":42,"w":16,"h":16},
	"rotated": false,
	"trimmed": false,
	"spriteSourceSize": {"x":0,"y":0,"w":16,"h":16},
	"sourceSize": {"w":16,"h":16},
	"anchor": {"x":0,"y":0}
},
"beach-1101.png":
{
	"frame": {"x":323,"y":37,"w":16,"h":16},
	"rotated": false,
	"trimmed": false,
	"spriteSourceSize": {"x":0,"y":0,"w":16,"h":16},
	"sourceSize": {"w":16,"h":16},
	"anchor": {"x":0,"y":0}
},
"beach-1102.png":
{
	"frame": {"x":72,"y":72,"w":16,"h":16},
	"rotated": false,
	"trimmed": false,
	"spriteSourceSize": {"x":0,"y":0,"w":16,"h":16},
	"sourceSize": {"w":16,"h":16},
	"anchor": {"x":0,"y":0}
},
"beach-1110.png":
{
	"frame": {"x":55,"y":93,"w":16,"h":16},
	"rotated": false,
	"trimmed": false,
	"spriteSourceSize": {"x":0,"y":0,"w":16,"h":16},
	"sourceSize": {"w":16,"h":16},
	"anchor": {"x":0,"y":0}
},
"beach-1120.png":
{
	"frame": {"x":90,"y":69,"w":16,"h":16},
	"rotated": false,
	"trimmed": false,
	"spriteSourceSize": {"x":0,"y":0,"w":16,"h":16},
	"sourceSize": {"w":16,"h":16},
	"anchor": {"x":0,"y":0}
},
"beach-1122.png":
{
	"frame": {"x":108,"y":67,"w":16,"h":16},
	"rotated": false,
	"trimmed": false,
	"spriteSourceSize": {"x":0,"y":0,"w":16,"h":16},
	"sourceSize": {"w":16,"h":16},
	"anchor": {"x":0,"y":0}
},
"beach-1200.png":
{
	"frame": {"x":487,"y":91,"w":16,"h":14},
	"rotated": true,
	"trimmed": true,
	"spriteSourceSize": {"x":0,"y":0,"w":16,"h":14},
	"sourceSize": {"w":16,"h":16},
	"anchor": {"x":0,"y":0}
},
"beach-1201.png":
{
	"frame": {"x":126,"y":66,"w":16,"h":16},
	"rotated": false,
	"trimmed": false,
	"spriteSourceSize": {"x":0,"y":0,"w":16,"h":16},
	"sourceSize": {"w":16,"h":16},
	"anchor": {"x":0,"y":0}
},
"beach-1202.png":
{
	"frame": {"x":503,"y":91,"w":16,"h":14},
	"rotated": false,
	"trimmed": true,
	"spriteSourceSize": {"x":0,"y":0,"w":16,"h":14},
	"sourceSize": {"w":16,"h":16},
	"anchor": {"x":0,"y":0}
},
"beach-1220.png":
{
	"frame": {"x":487,"y":91,"w":16,"h":14},
	"rotated": true,
	"trimmed": true,
	"spriteSourceSize": {"x":0,"y":0,"w":16,"h":14},
	"sourceSize": {"w":16,"h":16},
	"anchor": {"x":0,"y":0}
},
"beach-1221.png":
{
	"frame": {"x":144,"y":65,"w":16,"h":16},
	"rotated": false,
	"trimmed": false,
	"spriteSourceSize": {"x":0,"y":0,"w":16,"h":16},
	"sourceSize": {"w":16,"h":16},
	"anchor": {"x":0,"y":0}
},
"beach-1222.png":
{
	"frame": {"x":503,"y":91,"w":16,"h":14},
	"rotated": false,
	"trimmed": true,
	"spriteSourceSize": {"x":0,"y":0,"w":16,"h":14},
	"sourceSize": {"w":16,"h":16},
	"anchor": {"x":0,"y":0}
},
"beach-2001.png":
{
	"frame": {"x":634,"y":91,"w":12,"h":16},
	"rotated": false,
	"trimmed": true,
	"spriteSourceSize": {"x":0,"y":0,"w":12,"h":16},
	"sourceSize": {"w":16,"h":16},
	"anchor": {"x":0,"y":0}
},
"beach-2010.png":
{
	"frame": {"x":289,"y":114,"w":16,"h":11},
	"rotated": false,
	"trimmed": true,
	"spriteSourceSize": {"x":0,"y":5,"w":16,"h":11},
	"sourceSize": {"w":16,"h":16},
	"anchor": {"x":0,"y":0}
},
"beach-2011.png":
{
	"frame": {"x":162,"y":64,"w":16,"h":16},
	"rotated": false,
	"trimmed": false,
	"spriteSourceSize": {"x":0,"y":0,"w":16,"h":16},
	"sourceSize": {"w":16,"h":16},
	"anchor": {"x":0,"y":0}
},
"beach-2012.png":
{
	"frame": {"x":235,"y":115,"w":16,"h":10},
	"rotated": false,
	"trimmed": true,
	"spriteSourceSize": {"x":0,"y":6,"w":16,"h":10},
	"sourceSize": {"w":16,"h":16},
	"anchor": {"x":0,"y":0}
},
"beach-2021.png":
{
	"frame": {"x":634,"y":109,"w":12,"h":16},
	"rotated": false,
	"trimmed": true,
	"spriteSourceSize": {"x":0,"y":0,"w":12,"h":16},
	"sourceSize": {"w":16,"h":16},
	"anchor": {"x":0,"y":0}
},
"beach-2100.png":
{
	"frame": {"x":648,"y":91,"w":12,"h":16},
	"rotated": false,
	"trimmed": true,
	"spriteSourceSize": {"x":4,"y":0,"w":12,"h":16},
	"sourceSize": {"w":16,"h":16},
	"anchor": {"x":0,"y":0}
},
"beach-2102.png":
{
	"frame": {"x":648,"y":91,"w":12,"h":16},
	"rotated": false,
	"trimmed": true,
	"spriteSourceSize": {"x":4,"y":0,"w":12,"h":16},
	"sourceSize": {"w":16,"h":16},
	"anchor": {"x":0,"y":0}
},
"beach-2110.png":
{
	"frame": {"x":180,"y":63,"w":16,"h":16},
	"rotated": false,
	"trimmed": false,
	"spriteSourceSize": {"x":0,"y":0,"w":16,"h":16},
	"sourceSize": {"w":16,"h":16},
	"anchor": {"x":0,"y":0}
},
"beach-2112.png":
{
	"frame": {"x":198,"y":62,"w":16,"h":16},
	"rotated": false,
	"trimmed": false,
	"spriteSourceSize": {"x":0,"y":0,"w":16,"h":16},
	"sourceSize": {"w":16,"h":16},
	"anchor": {"x":0,"y":0}
},
"beach-2120.png":
{
	"frame": {"x":648,"y":109,"w":12,"h":16},
	"rotated": false,
	"trimmed": true,
	"spriteSourceSize": {"x":4,"y":0,"w":12,"h":16},
	"sourceSize": {"w":16,"h":16},
	"anchor": {"x":0,"y":0}
},
"beach-2122.png":
{
	"frame": {"x":648,"y":109,"w":12,"h":16},
	"rotated": false,
	"trimmed": true,
	"spriteSourceSize": {"x":4,"y":0,"w":12,"h":16},
	"sourceSize": {"w":16,"h":16},
	"anchor": {"x":0,"y":0}
},
"beach-2201.png":
{
	"frame": {"x":634,"y":91,"w":12,"h":16},
	"rotated": false,
	"trimmed": true,
	"spriteSourceSize": {"x":0,"y":0,"w":12,"h":16},
	"sourceSize": {"w":16,"h":16},
	"anchor": {"x":0,"y":0}
},
"beach-2210.png":
{
	"frame": {"x":253,"y":115,"w":16,"h":10},
	"rotated": false,
	"trimmed": true,
	"spriteSourceSize": {"x":0,"y":6,"w":16,"h":10},
	"sourceSize": {"w":16,"h":16},
	"anchor": {"x":0,"y":0}
},
"beach-2211.png":
{
	"frame": {"x":216,"y":62,"w":16,"h":16},
	"rotated": false,
	"trimmed": false,
	"spriteSourceSize": {"x":0,"y":0,"w":16,"h":16},
	"sourceSize": {"w":16,"h":16},
	"anchor": {"x":0,"y":0}
},
"beach-2212.png":
{
	"frame": {"x":271,"y":115,"w":16,"h":10},
	"rotated": false,
	"trimmed": true,
	"spriteSourceSize": {"x":0,"y":6,"w":16,"h":10},
	"sourceSize": {"w":16,"h":16},
	"anchor": {"x":0,"y":0}
},
"beach-2221.png":
{
	"frame": {"x":634,"y":109,"w":12,"h":16},
	"rotated": false,
	"trimmed": true,
	"spriteSourceSize": {"x":0,"y":0,"w":12,"h":16},
	"sourceSize": {"w":16,"h":16},
	"anchor": {"x":0,"y":0}
},
"beach.png":
{
	"frame": {"x":107,"y":29,"w":16,"h":17},
	"rotated": false,
	"trimmed": true,
	"spriteSourceSize": {"x":0,"y":15,"w":16,"h":17},
	"sourceSize": {"w":16,"h":32},
	"anchor": {"x":0,"y":0.5}
},
"bridge-0000.png":
{
	"frame": {"x":307,"y":114,"w":16,"h":11},
	"rotated": false,
	"trimmed": true,
	"spriteSourceSize": {"x":0,"y":3,"w":16,"h":11},
	"sourceSize": {"w":16,"h":16},
	"anchor": {"x":0,"y":0}
},
"bridge-0001.png":
{
	"frame": {"x":307,"y":114,"w":16,"h":11},
	"rotated": false,
	"trimmed": true,
	"spriteSourceSize": {"x":0,"y":3,"w":16,"h":11},
	"sourceSize": {"w":16,"h":16},
	"anchor": {"x":0,"y":0}
},
"bridge-0010.png":
{
	"frame": {"x":734,"y":91,"w":10,"h":16},
	"rotated": true,
	"trimmed": true,
	"spriteSourceSize": {"x":3,"y":0,"w":10,"h":16},
	"sourceSize": {"w":16,"h":16},
	"anchor": {"x":0,"y":0}
},
"bridge-0011.png":
{
	"frame": {"x":784,"y":91,"w":13,"h":13},
	"rotated": false,
	"trimmed": true,
	"spriteSourceSize": {"x":0,"y":3,"w":13,"h":13},
	"sourceSize": {"w":16,"h":16},
	"anchor": {"x":0,"y":0}
},
"bridge-0100.png":
{
	"frame": {"x":307,"y":114,"w":16,"h":11},
	"rotated": false,
	"trimmed": true,
	"spriteSourceSize": {"x":0,"y":3,"w":16,"h":11},
	"sourceSize": {"w":16,"h":16},
	"anchor": {"x":0,"y":0}
},
"bridge-0101.png":
{
	"frame": {"x":307,"y":114,"w":16,"h":11},
	"rotated": false,
	"trimmed": true,
	"spriteSourceSize": {"x":0,"y":3,"w":16,"h":11},
	"sourceSize": {"w":16,"h":16},
	"anchor": {"x":0,"y":0}
},
"bridge-0110.png":
{
	"frame": {"x":700,"y":103,"w":13,"h":13},
	"rotated": false,
	"trimmed": true,
	"spriteSourceSize": {"x":3,"y":3,"w":13,"h":13},
	"sourceSize": {"w":16,"h":16},
	"anchor": {"x":0,"y":0}
},
"bridge-0111.png":
{
	"frame": {"x":605,"y":109,"w":16,"h":13},
	"rotated": true,
	"trimmed": true,
	"spriteSourceSize": {"x":0,"y":3,"w":16,"h":13},
	"sourceSize": {"w":16,"h":16},
	"anchor": {"x":0,"y":0}
},
"bridge-1000.png":
{
	"frame": {"x":734,"y":91,"w":10,"h":16},
	"rotated": true,
	"trimmed": true,
	"spriteSourceSize": {"x":3,"y":0,"w":10,"h":16},
	"sourceSize": {"w":16,"h":16},
	"anchor": {"x":0,"y":0}
},
"bridge-1001.png":
{
	"frame": {"x":752,"y":91,"w":13,"h":14},
	"rotated": true,
	"trimmed": true,
	"spriteSourceSize": {"x":0,"y":0,"w":13,"h":14},
	"sourceSize": {"w":16,"h":16},
	"anchor": {"x":0,"y":0}
},
"bridge-1010.png":
{
	"frame": {"x":734,"y":91,"w":10,"h":16},
	"rotated": true,
	"trimmed": true,
	"spriteSourceSize": {"x":3,"y":0,"w":10,"h":16},
	"sourceSize": {"w":16,"h":16},
	"anchor": {"x":0,"y":0}
},
"bridge-1011.png":
{
	"frame": {"x":575,"y":109,"w":13,"h":16},
	"rotated": false,
	"trimmed": true,
	"spriteSourceSize": {"x":0,"y":0,"w":13,"h":16},
	"sourceSize": {"w":16,"h":16},
	"anchor": {"x":0,"y":0}
},
"bridge-1100.png":
{
	"frame": {"x":768,"y":91,"w":13,"h":14},
	"rotated": true,
	"trimmed": true,
	"spriteSourceSize": {"x":3,"y":0,"w":13,"h":14},
	"sourceSize": {"w":16,"h":16},
	"anchor": {"x":0,"y":0}
},
"bridge-1101.png":
{
	"frame": {"x":503,"y":107,"w":16,"h":14},
	"rotated": false,
	"trimmed": true,
	"spriteSourceSize": {"x":0,"y":0,"w":16,"h":14},
	"sourceSize": {"w":16,"h":16},
	"anchor": {"x":0,"y":0}
},
"bridge-1110.png":
{
	"frame": {"x":590,"y":91,"w":13,"h":16},
	"rotated": false,
	"trimmed": true,
	"spriteSourceSize": {"x":3,"y":0,"w":13,"h":16},
	"sourceSize": {"w":16,"h":16},
	"anchor": {"x":0,"y":0}
},
"bridge-1111.png":
{
	"frame": {"x":234,"y":61,"w":16,"h":16},
	"rotated": false,
	"trimmed": false,
	"spriteSourceSize": {"x":0,"y":0,"w":16,"h":16},
	"sourceSize": {"w":16,"h":16},
	"anchor": {"x":0,"y":0}
},
"bridge.png":
{
	"frame": {"x":125,"y":28,"w":16,"h":17},
	"rotated": false,
	"trimmed": true,
	"spriteSourceSize": {"x":0,"y":15,"w":16,"h":17},
	"sourceSize": {"w":16,"h":32},
	"anchor": {"x":0,"y":0.5}
},
"city-white.png":
{
	"frame": {"x":37,"y":56,"w":15,"h":19},
	"rotated": false,
	"trimmed": true,
	"spriteSourceSize": {"x":1,"y":13,"w":15,"h":19},
	"sourceSize": {"w":16,"h":32},
	"anchor": {"x":0,"y":0.5}
},
"city.png":
{
	"frame": {"x":37,"y":77,"w":16,"h":19},
	"rotated": false,
	"trimmed": true,
	"spriteSourceSize": {"x":0,"y":13,"w":16,"h":19},
	"sourceSize": {"w":16,"h":32},
	"anchor": {"x":0,"y":0.5}
},
"coms-white.png":
{
	"frame": {"x":323,"y":1,"w":15,"h":21},
	"rotated": true,
	"trimmed": true,
	"spriteSourceSize": {"x":1,"y":11,"w":15,"h":21},
	"sourceSize": {"w":16,"h":32},
	"anchor": {"x":0,"y":0.5}
},
"coms.png":
{
	"frame": {"x":233,"y":1,"w":16,"h":21},
	"rotated": false,
	"trimmed": true,
	"spriteSourceSize": {"x":0,"y":11,"w":16,"h":21},
	"sourceSize": {"w":16,"h":32},
	"anchor": {"x":0,"y":0.5}
},
"factory-white.png":
{
	"frame": {"x":72,"y":53,"w":15,"h":17},
	"rotated": false,
	"trimmed": true,
	"spriteSourceSize": {"x":1,"y":15,"w":15,"h":17},
	"sourceSize": {"w":16,"h":32},
	"anchor": {"x":0,"y":0.5}
},
"factory.png":
{
	"frame": {"x":143,"y":27,"w":16,"h":17},
	"rotated": false,
	"trimmed": true,
	"spriteSourceSize": {"x":0,"y":15,"w":16,"h":17},
	"sourceSize": {"w":16,"h":32},
	"anchor": {"x":0,"y":0.5}
},
"fire-0.png":
{
	"frame": {"x":89,"y":1,"w":16,"h":26},
	"rotated": false,
	"trimmed": true,
	"spriteSourceSize": {"x":0,"y":6,"w":16,"h":26},
	"sourceSize": {"w":16,"h":32},
	"anchor": {"x":0,"y":0.5}
},
"fire-1.png":
{
	"frame": {"x":53,"y":1,"w":16,"h":29},
	"rotated": false,
	"trimmed": true,
	"spriteSourceSize": {"x":0,"y":3,"w":16,"h":29},
	"sourceSize": {"w":16,"h":32},
	"anchor": {"x":0,"y":0.5}
},
"fire-2.png":
{
	"frame": {"x":1,"y":68,"w":16,"h":30},
	"rotated": false,
	"trimmed": true,
	"spriteSourceSize": {"x":0,"y":2,"w":16,"h":30},
	"sourceSize": {"w":16,"h":32},
	"anchor": {"x":0,"y":0.5}
},
"fire-3.png":
{
	"frame": {"x":1,"y":35,"w":16,"h":31},
	"rotated": false,
	"trimmed": true,
	"spriteSourceSize": {"x":0,"y":1,"w":16,"h":31},
	"sourceSize": {"w":16,"h":32},
	"anchor": {"x":0,"y":0.5}
},
"fire-4.png":
{
	"frame": {"x":35,"y":1,"w":16,"h":31},
	"rotated": false,
	"trimmed": true,
	"spriteSourceSize": {"x":0,"y":1,"w":16,"h":31},
	"sourceSize": {"w":16,"h":32},
	"anchor": {"x":0,"y":0.5}
},
"fire-5.png":
{
	"frame": {"x":71,"y":1,"w":16,"h":29},
	"rotated": false,
	"trimmed": true,
	"spriteSourceSize": {"x":0,"y":3,"w":16,"h":29},
	"sourceSize": {"w":16,"h":32},
	"anchor": {"x":0,"y":0.5}
},
"fire.png":
{
	"frame": {"x":107,"y":1,"w":16,"h":26},
	"rotated": false,
	"trimmed": true,
	"spriteSourceSize": {"x":0,"y":6,"w":16,"h":26},
	"sourceSize": {"w":16,"h":32},
	"anchor": {"x":0,"y":0.5}
},
"hq-white.png":
{
	"frame": {"x":1,"y":100,"w":16,"h":25},
	"rotated": false,
	"trimmed": true,
	"spriteSourceSize": {"x":0,"y":7,"w":16,"h":25},
	"sourceSize": {"w":16,"h":32},
	"anchor": {"x":0,"y":0.5}
},
"hq.png":
{
	"frame": {"x":125,"y":1,"w":16,"h":25},
	"rotated": false,
	"trimmed": true,
	"spriteSourceSize": {"x":0,"y":7,"w":16,"h":25},
	"sourceSize": {"w":16,"h":32},
	"anchor": {"x":0,"y":0.5}
},
"meteor-0000.png":
{
	"frame": {"x":346,"y":1,"w":16,"h":20},
	"rotated": true,
	"trimmed": true,
	"spriteSourceSize": {"x":0,"y":12,"w":16,"h":20},
	"sourceSize": {"w":16,"h":32},
	"anchor": {"x":0,"y":0.5}
},
"meteor-1-0001.png":
{
	"frame": {"x":368,"y":1,"w":16,"h":20},
	"rotated": true,
	"trimmed": true,
	"spriteSourceSize": {"x":0,"y":12,"w":16,"h":20},
	"sourceSize": {"w":16,"h":32},
	"anchor": {"x":0,"y":0.5}
},
"meteor-1-0010.png":
{
	"frame": {"x":390,"y":1,"w":16,"h":20},
	"rotated": true,
	"trimmed": true,
	"spriteSourceSize": {"x":0,"y":12,"w":16,"h":20},
	"sourceSize": {"w":16,"h":32},
	"anchor": {"x":0,"y":0.5}
},
"meteor-1-0011.png":
{
	"frame": {"x":412,"y":1,"w":16,"h":20},
	"rotated": true,
	"trimmed": true,
	"spriteSourceSize": {"x":0,"y":12,"w":16,"h":20},
	"sourceSize": {"w":16,"h":32},
	"anchor": {"x":0,"y":0.5}
},
"meteor-1-0100.png":
{
	"frame": {"x":434,"y":1,"w":16,"h":20},
	"rotated": true,
	"trimmed": true,
	"spriteSourceSize": {"x":0,"y":12,"w":16,"h":20},
	"sourceSize": {"w":16,"h":32},
	"anchor": {"x":0,"y":0.5}
},
"meteor-1-0101.png":
{
	"frame": {"x":456,"y":1,"w":16,"h":20},
	"rotated": true,
	"trimmed": true,
	"spriteSourceSize": {"x":0,"y":12,"w":16,"h":20},
	"sourceSize": {"w":16,"h":32},
	"anchor": {"x":0,"y":0.5}
},
"meteor-1-0110.png":
{
	"frame": {"x":478,"y":1,"w":16,"h":20},
	"rotated": true,
	"trimmed": true,
	"spriteSourceSize": {"x":0,"y":12,"w":16,"h":20},
	"sourceSize": {"w":16,"h":32},
	"anchor": {"x":0,"y":0.5}
},
"meteor-1-0111.png":
{
	"frame": {"x":500,"y":1,"w":16,"h":20},
	"rotated": true,
	"trimmed": true,
	"spriteSourceSize": {"x":0,"y":12,"w":16,"h":20},
	"sourceSize": {"w":16,"h":32},
	"anchor": {"x":0,"y":0.5}
},
"meteor-2-0001.png":
{
	"frame": {"x":522,"y":1,"w":16,"h":20},
	"rotated": true,
	"trimmed": true,
	"spriteSourceSize": {"x":0,"y":12,"w":16,"h":20},
	"sourceSize": {"w":16,"h":32},
	"anchor": {"x":0,"y":0.5}
},
"meteor-2-0010.png":
{
	"frame": {"x":544,"y":1,"w":16,"h":20},
	"rotated": true,
	"trimmed": true,
	"spriteSourceSize": {"x":0,"y":12,"w":16,"h":20},
	"sourceSize": {"w":16,"h":32},
	"anchor": {"x":0,"y":0.5}
},
"meteor-2-0011.png":
{
	"frame": {"x":566,"y":1,"w":16,"h":20},
	"rotated": true,
	"trimmed": true,
	"spriteSourceSize": {"x":0,"y":12,"w":16,"h":20},
	"sourceSize": {"w":16,"h":32},
	"anchor": {"x":0,"y":0.5}
},
"meteor-2-0100.png":
{
	"frame": {"x":588,"y":1,"w":16,"h":20},
	"rotated": true,
	"trimmed": true,
	"spriteSourceSize": {"x":0,"y":12,"w":16,"h":20},
	"sourceSize": {"w":16,"h":32},
	"anchor": {"x":0,"y":0.5}
},
"meteor-2-0101.png":
{
	"frame": {"x":610,"y":1,"w":16,"h":20},
	"rotated": true,
	"trimmed": true,
	"spriteSourceSize": {"x":0,"y":12,"w":16,"h":20},
	"sourceSize": {"w":16,"h":32},
	"anchor": {"x":0,"y":0.5}
},
"meteor-2-0110.png":
{
	"frame": {"x":632,"y":1,"w":16,"h":20},
	"rotated": true,
	"trimmed": true,
	"spriteSourceSize": {"x":0,"y":12,"w":16,"h":20},
	"sourceSize": {"w":16,"h":32},
	"anchor": {"x":0,"y":0.5}
},
"meteor-2-0111.png":
{
	"frame": {"x":654,"y":1,"w":16,"h":20},
	"rotated": true,
	"trimmed": true,
	"spriteSourceSize": {"x":0,"y":12,"w":16,"h":20},
	"sourceSize": {"w":16,"h":32},
	"anchor": {"x":0,"y":0.5}
},
"meteor-3-0001.png":
{
	"frame": {"x":676,"y":1,"w":16,"h":20},
	"rotated": true,
	"trimmed": true,
	"spriteSourceSize": {"x":0,"y":12,"w":16,"h":20},
	"sourceSize": {"w":16,"h":32},
	"anchor": {"x":0,"y":0.5}
},
"meteor-3-0010.png":
{
	"frame": {"x":698,"y":1,"w":16,"h":20},
	"rotated": true,
	"trimmed": true,
	"spriteSourceSize": {"x":0,"y":12,"w":16,"h":20},
	"sourceSize": {"w":16,"h":32},
	"anchor": {"x":0,"y":0.5}
},
"meteor-3-0011.png":
{
	"frame": {"x":720,"y":1,"w":16,"h":20},
	"rotated": true,
	"trimmed": true,
	"spriteSourceSize": {"x":0,"y":12,"w":16,"h":20},
	"sourceSize": {"w":16,"h":32},
	"anchor": {"x":0,"y":0.5}
},
"meteor-3-0100.png":
{
	"frame": {"x":742,"y":1,"w":16,"h":20},
	"rotated": true,
	"trimmed": true,
	"spriteSourceSize": {"x":0,"y":12,"w":16,"h":20},
	"sourceSize": {"w":16,"h":32},
	"anchor": {"x":0,"y":0.5}
},
"meteor-3-0101.png":
{
	"frame": {"x":764,"y":1,"w":16,"h":20},
	"rotated": true,
	"trimmed": true,
	"spriteSourceSize": {"x":0,"y":12,"w":16,"h":20},
	"sourceSize": {"w":16,"h":32},
	"anchor": {"x":0,"y":0.5}
},
"meteor-3-0110.png":
{
	"frame": {"x":786,"y":1,"w":16,"h":20},
	"rotated": true,
	"trimmed": true,
	"spriteSourceSize": {"x":0,"y":12,"w":16,"h":20},
	"sourceSize": {"w":16,"h":32},
	"anchor": {"x":0,"y":0.5}
},
"meteor-3-0111.png":
{
	"frame": {"x":808,"y":1,"w":16,"h":20},
	"rotated": false,
	"trimmed": true,
	"spriteSourceSize": {"x":0,"y":12,"w":16,"h":20},
	"sourceSize": {"w":16,"h":32},
	"anchor": {"x":0,"y":0.5}
},
"meteor.png":
{
	"frame": {"x":37,"y":98,"w":16,"h":19},
	"rotated": false,
	"trimmed": true,
	"spriteSourceSize": {"x":0,"y":13,"w":16,"h":19},
	"sourceSize": {"w":16,"h":32},
	"anchor": {"x":0,"y":0.5}
},
"mist-00.png":
{
	"frame": {"x":54,"y":32,"w":16,"h":19},
	"rotated": false,
	"trimmed": true,
	"spriteSourceSize": {"x":0,"y":13,"w":16,"h":19},
	"sourceSize": {"w":16,"h":32},
	"anchor": {"x":0,"y":0.5}
},
"mist-01.png":
{
	"frame": {"x":19,"y":35,"w":16,"h":20},
	"rotated": false,
	"trimmed": true,
	"spriteSourceSize": {"x":0,"y":12,"w":16,"h":20},
	"sourceSize": {"w":16,"h":32},
	"anchor": {"x":0,"y":0.5}
},
"mist-10.png":
{
	"frame": {"x":19,"y":57,"w":16,"h":20},
	"rotated": false,
	"trimmed": true,
	"spriteSourceSize": {"x":0,"y":12,"w":16,"h":20},
	"sourceSize": {"w":16,"h":32},
	"anchor": {"x":0,"y":0.5}
},
"mist-11.png":
{
	"frame": {"x":19,"y":79,"w":16,"h":20},
	"rotated": false,
	"trimmed": true,
	"spriteSourceSize": {"x":0,"y":12,"w":16,"h":20},
	"sourceSize": {"w":16,"h":32},
	"anchor": {"x":0,"y":0.5}
},
"mist.png":
{
	"frame": {"x":54,"y":53,"w":16,"h":19},
	"rotated": false,
	"trimmed": true,
	"spriteSourceSize": {"x":0,"y":13,"w":16,"h":19},
	"sourceSize": {"w":16,"h":32},
	"anchor": {"x":0,"y":0.5}
},
"mountain-00.png":
{
	"frame": {"x":197,"y":1,"w":16,"h":22},
	"rotated": false,
	"trimmed": true,
	"spriteSourceSize": {"x":0,"y":10,"w":16,"h":22},
	"sourceSize": {"w":16,"h":32},
	"anchor": {"x":0,"y":0.5}
},
"mountain-01.png":
{
	"frame": {"x":179,"y":1,"w":16,"h":23},
	"rotated": false,
	"trimmed": true,
	"spriteSourceSize": {"x":0,"y":9,"w":16,"h":23},
	"sourceSize": {"w":16,"h":32},
	"anchor": {"x":0,"y":0.5}
},
"mountain-10.png":
{
	"frame": {"x":143,"y":1,"w":16,"h":24},
	"rotated": false,
	"trimmed": true,
	"spriteSourceSize": {"x":0,"y":8,"w":16,"h":24},
	"sourceSize": {"w":16,"h":32},
	"anchor": {"x":0,"y":0.5}
},
"mountain-11.png":
{
	"frame": {"x":161,"y":1,"w":16,"h":24},
	"rotated": false,
	"trimmed": true,
	"spriteSourceSize": {"x":0,"y":8,"w":16,"h":24},
	"sourceSize": {"w":16,"h":32},
	"anchor": {"x":0,"y":0.5}
},
"mountain.png":
{
	"frame": {"x":215,"y":1,"w":16,"h":22},
	"rotated": false,
	"trimmed": true,
	"spriteSourceSize": {"x":0,"y":10,"w":16,"h":22},
	"sourceSize": {"w":16,"h":32},
	"anchor": {"x":0,"y":0.5}
},
"plain-0.png":
{
	"frame": {"x":252,"y":61,"w":16,"h":16},
	"rotated": false,
	"trimmed": false,
	"spriteSourceSize": {"x":0,"y":0,"w":16,"h":16},
	"sourceSize": {"w":16,"h":16},
	"anchor": {"x":0,"y":0}
},
"plain-0000.png":
{
	"frame": {"x":270,"y":61,"w":16,"h":16},
	"rotated": false,
	"trimmed": false,
	"spriteSourceSize": {"x":0,"y":0,"w":16,"h":16},
	"sourceSize": {"w":16,"h":16},
	"anchor": {"x":0,"y":0}
},
"plain-0001.png":
{
	"frame": {"x":288,"y":60,"w":16,"h":16},
	"rotated": false,
	"trimmed": false,
	"spriteSourceSize": {"x":0,"y":0,"w":16,"h":16},
	"sourceSize": {"w":16,"h":16},
	"anchor": {"x":0,"y":0}
},
"plain-1.png":
{
	"frame": {"x":109,"y":103,"w":16,"h":16},
	"rotated": false,
	"trimmed": false,
	"spriteSourceSize": {"x":0,"y":0,"w":16,"h":16},
	"sourceSize": {"w":16,"h":16},
	"anchor": {"x":0,"y":0}
},
"plain-2.png":
{
	"frame": {"x":199,"y":80,"w":16,"h":16},
	"rotated": false,
	"trimmed": false,
	"spriteSourceSize": {"x":0,"y":0,"w":16,"h":16},
	"sourceSize": {"w":16,"h":16},
	"anchor": {"x":0,"y":0}
},
"plain-3.png":
{
	"frame": {"x":199,"y":98,"w":16,"h":16},
	"rotated": false,
	"trimmed": false,
	"spriteSourceSize": {"x":0,"y":0,"w":16,"h":16},
	"sourceSize": {"w":16,"h":16},
	"anchor": {"x":0,"y":0}
},
"plain-4.png":
{
	"frame": {"x":217,"y":80,"w":16,"h":16},
	"rotated": false,
	"trimmed": false,
	"spriteSourceSize": {"x":0,"y":0,"w":16,"h":16},
	"sourceSize": {"w":16,"h":16},
	"anchor": {"x":0,"y":0}
},
"plain-5.png":
{
	"frame": {"x":217,"y":98,"w":16,"h":16},
	"rotated": false,
	"trimmed": false,
	"spriteSourceSize": {"x":0,"y":0,"w":16,"h":16},
	"sourceSize": {"w":16,"h":16},
	"anchor": {"x":0,"y":0}
},
"plain-6.png":
{
	"frame": {"x":235,"y":79,"w":16,"h":16},
	"rotated": false,
	"trimmed": false,
	"spriteSourceSize": {"x":0,"y":0,"w":16,"h":16},
	"sourceSize": {"w":16,"h":16},
	"anchor": {"x":0,"y":0}
},
"plain-0010.png":
{
	"frame": {"x":306,"y":60,"w":16,"h":16},
	"rotated": false,
	"trimmed": false,
	"spriteSourceSize": {"x":0,"y":0,"w":16,"h":16},
	"sourceSize": {"w":16,"h":16},
	"anchor": {"x":0,"y":0}
},
"plain-0011.png":
{
	"frame": {"x":73,"y":90,"w":16,"h":16},
	"rotated": false,
	"trimmed": false,
	"spriteSourceSize": {"x":0,"y":0,"w":16,"h":16},
	"sourceSize": {"w":16,"h":16},
	"anchor": {"x":0,"y":0}
},
"plain-0100.png":
{
	"frame": {"x":73,"y":108,"w":16,"h":16},
	"rotated": false,
	"trimmed": false,
	"spriteSourceSize": {"x":0,"y":0,"w":16,"h":16},
	"sourceSize": {"w":16,"h":16},
	"anchor": {"x":0,"y":0}
},
"plain-0101.png":
{
	"frame": {"x":91,"y":87,"w":16,"h":16},
	"rotated": false,
	"trimmed": false,
	"spriteSourceSize": {"x":0,"y":0,"w":16,"h":16},
	"sourceSize": {"w":16,"h":16},
	"anchor": {"x":0,"y":0}
},
"plain-0110.png":
{
	"frame": {"x":91,"y":105,"w":16,"h":16},
	"rotated": false,
	"trimmed": false,
	"spriteSourceSize": {"x":0,"y":0,"w":16,"h":16},
	"sourceSize": {"w":16,"h":16},
	"anchor": {"x":0,"y":0}
},
"plain-0111.png":
{
	"frame": {"x":109,"y":85,"w":16,"h":16},
	"rotated": false,
	"trimmed": false,
	"spriteSourceSize": {"x":0,"y":0,"w":16,"h":16},
	"sourceSize": {"w":16,"h":16},
	"anchor": {"x":0,"y":0}
},
"plain-1000.png":
{
	"frame": {"x":127,"y":84,"w":16,"h":16},
	"rotated": false,
	"trimmed": false,
	"spriteSourceSize": {"x":0,"y":0,"w":16,"h":16},
	"sourceSize": {"w":16,"h":16},
	"anchor": {"x":0,"y":0}
},
"plain-1001.png":
{
	"frame": {"x":127,"y":102,"w":16,"h":16},
	"rotated": false,
	"trimmed": false,
	"spriteSourceSize": {"x":0,"y":0,"w":16,"h":16},
	"sourceSize": {"w":16,"h":16},
	"anchor": {"x":0,"y":0}
},
"plain-1010.png":
{
	"frame": {"x":145,"y":83,"w":16,"h":16},
	"rotated": false,
	"trimmed": false,
	"spriteSourceSize": {"x":0,"y":0,"w":16,"h":16},
	"sourceSize": {"w":16,"h":16},
	"anchor": {"x":0,"y":0}
},
"plain-1011.png":
{
	"frame": {"x":145,"y":101,"w":16,"h":16},
	"rotated": false,
	"trimmed": false,
	"spriteSourceSize": {"x":0,"y":0,"w":16,"h":16},
	"sourceSize": {"w":16,"h":16},
	"anchor": {"x":0,"y":0}
},
"plain-1100.png":
{
	"frame": {"x":163,"y":82,"w":16,"h":16},
	"rotated": false,
	"trimmed": false,
	"spriteSourceSize": {"x":0,"y":0,"w":16,"h":16},
	"sourceSize": {"w":16,"h":16},
	"anchor": {"x":0,"y":0}
},
"plain-1101.png":
{
	"frame": {"x":163,"y":100,"w":16,"h":16},
	"rotated": false,
	"trimmed": false,
	"spriteSourceSize": {"x":0,"y":0,"w":16,"h":16},
	"sourceSize": {"w":16,"h":16},
	"anchor": {"x":0,"y":0}
},
"plain-1110.png":
{
	"frame": {"x":181,"y":81,"w":16,"h":16},
	"rotated": false,
	"trimmed": false,
	"spriteSourceSize": {"x":0,"y":0,"w":16,"h":16},
	"sourceSize": {"w":16,"h":16},
	"anchor": {"x":0,"y":0}
},
"plain-1111.png":
{
	"frame": {"x":181,"y":99,"w":16,"h":16},
	"rotated": false,
	"trimmed": false,
	"spriteSourceSize": {"x":0,"y":0,"w":16,"h":16},
	"sourceSize": {"w":16,"h":16},
	"anchor": {"x":0,"y":0}
},
"plain-crag.png":
{
	"frame": {"x":235,"y":97,"w":16,"h":16},
	"rotated": false,
	"trimmed": false,
	"spriteSourceSize": {"x":0,"y":0,"w":16,"h":16},
	"sourceSize": {"w":16,"h":16},
	"anchor": {"x":0,"y":0}
},
"plain-crater.png":
{
	"frame": {"x":253,"y":79,"w":16,"h":16},
	"rotated": false,
	"trimmed": false,
	"spriteSourceSize": {"x":0,"y":0,"w":16,"h":16},
	"sourceSize": {"w":16,"h":16},
	"anchor": {"x":0,"y":0}
},
"plain.png":
{
	"frame": {"x":161,"y":27,"w":16,"h":17},
	"rotated": false,
	"trimmed": true,
	"spriteSourceSize": {"x":0,"y":15,"w":16,"h":17},
	"sourceSize": {"w":16,"h":32},
	"anchor": {"x":0,"y":0.5}
},
"plasma-1-0000.png":
{
	"frame": {"x":253,"y":97,"w":16,"h":16},
	"rotated": false,
	"trimmed": false,
	"spriteSourceSize": {"x":0,"y":0,"w":16,"h":16},
	"sourceSize": {"w":16,"h":16},
	"anchor": {"x":0,"y":0}
},
"plasma-1-0001.png":
{
	"frame": {"x":271,"y":79,"w":16,"h":16},
	"rotated": false,
	"trimmed": false,
	"spriteSourceSize": {"x":0,"y":0,"w":16,"h":16},
	"sourceSize": {"w":16,"h":16},
	"anchor": {"x":0,"y":0}
},
"plasma-1-0010.png":
{
	"frame": {"x":271,"y":97,"w":16,"h":16},
	"rotated": false,
	"trimmed": false,
	"spriteSourceSize": {"x":0,"y":0,"w":16,"h":16},
	"sourceSize": {"w":16,"h":16},
	"anchor": {"x":0,"y":0}
},
"plasma-1-0011.png":
{
	"frame": {"x":289,"y":78,"w":16,"h":16},
	"rotated": false,
	"trimmed": false,
	"spriteSourceSize": {"x":0,"y":0,"w":16,"h":16},
	"sourceSize": {"w":16,"h":16},
	"anchor": {"x":0,"y":0}
},
"plasma-1-0100.png":
{
	"frame": {"x":289,"y":96,"w":16,"h":16},
	"rotated": false,
	"trimmed": false,
	"spriteSourceSize": {"x":0,"y":0,"w":16,"h":16},
	"sourceSize": {"w":16,"h":16},
	"anchor": {"x":0,"y":0}
},
"plasma-1-0101.png":
{
	"frame": {"x":791,"y":37,"w":16,"h":15},
	"rotated": true,
	"trimmed": true,
	"spriteSourceSize": {"x":0,"y":0,"w":16,"h":15},
	"sourceSize": {"w":16,"h":16},
	"anchor": {"x":0,"y":0}
},
"plasma-1-0110.png":
{
	"frame": {"x":307,"y":96,"w":16,"h":16},
	"rotated": false,
	"trimmed": false,
	"spriteSourceSize": {"x":0,"y":0,"w":16,"h":16},
	"sourceSize": {"w":16,"h":16},
	"anchor": {"x":0,"y":0}
},
"plasma-1-0111.png":
{
	"frame": {"x":341,"y":19,"w":16,"h":16},
	"rotated": false,
	"trimmed": false,
	"spriteSourceSize": {"x":0,"y":0,"w":16,"h":16},
	"sourceSize": {"w":16,"h":16},
	"anchor": {"x":0,"y":0}
},
"plasma-1-1000.png":
{
	"frame": {"x":359,"y":19,"w":16,"h":16},
	"rotated": false,
	"trimmed": false,
	"spriteSourceSize": {"x":0,"y":0,"w":16,"h":16},
	"sourceSize": {"w":16,"h":16},
	"anchor": {"x":0,"y":0}
},
"plasma-1-1001.png":
{
	"frame": {"x":341,"y":37,"w":16,"h":16},
	"rotated": false,
	"trimmed": false,
	"spriteSourceSize": {"x":0,"y":0,"w":16,"h":16},
	"sourceSize": {"w":16,"h":16},
	"anchor": {"x":0,"y":0}
},
"plasma-1-1010.png":
{
	"frame": {"x":307,"y":78,"w":15,"h":16},
	"rotated": false,
	"trimmed": true,
	"spriteSourceSize": {"x":0,"y":0,"w":15,"h":16},
	"sourceSize": {"w":16,"h":16},
	"anchor": {"x":0,"y":0}
},
"plasma-1-1011.png":
{
	"frame": {"x":377,"y":19,"w":16,"h":16},
	"rotated": false,
	"trimmed": false,
	"spriteSourceSize": {"x":0,"y":0,"w":16,"h":16},
	"sourceSize": {"w":16,"h":16},
	"anchor": {"x":0,"y":0}
},
"plasma-1-1100.png":
{
	"frame": {"x":359,"y":37,"w":16,"h":16},
	"rotated": false,
	"trimmed": false,
	"spriteSourceSize": {"x":0,"y":0,"w":16,"h":16},
	"sourceSize": {"w":16,"h":16},
	"anchor": {"x":0,"y":0}
},
"plasma-1-1101.png":
{
	"frame": {"x":395,"y":19,"w":16,"h":16},
	"rotated": false,
	"trimmed": false,
	"spriteSourceSize": {"x":0,"y":0,"w":16,"h":16},
	"sourceSize": {"w":16,"h":16},
	"anchor": {"x":0,"y":0}
},
"plasma-1-1110.png":
{
	"frame": {"x":377,"y":37,"w":16,"h":16},
	"rotated": false,
	"trimmed": false,
	"spriteSourceSize": {"x":0,"y":0,"w":16,"h":16},
	"sourceSize": {"w":16,"h":16},
	"anchor": {"x":0,"y":0}
},
"plasma-1-1111.png":
{
	"frame": {"x":413,"y":19,"w":16,"h":16},
	"rotated": false,
	"trimmed": false,
	"spriteSourceSize": {"x":0,"y":0,"w":16,"h":16},
	"sourceSize": {"w":16,"h":16},
	"anchor": {"x":0,"y":0}
},
"plasma-2-0000.png":
{
	"frame": {"x":395,"y":37,"w":16,"h":16},
	"rotated": false,
	"trimmed": false,
	"spriteSourceSize": {"x":0,"y":0,"w":16,"h":16},
	"sourceSize": {"w":16,"h":16},
	"anchor": {"x":0,"y":0}
},
"plasma-2-0001.png":
{
	"frame": {"x":431,"y":19,"w":16,"h":16},
	"rotated": false,
	"trimmed": false,
	"spriteSourceSize": {"x":0,"y":0,"w":16,"h":16},
	"sourceSize": {"w":16,"h":16},
	"anchor": {"x":0,"y":0}
},
"plasma-2-0010.png":
{
	"frame": {"x":791,"y":19,"w":15,"h":16},
	"rotated": false,
	"trimmed": true,
	"spriteSourceSize": {"x":0,"y":0,"w":15,"h":16},
	"sourceSize": {"w":16,"h":16},
	"anchor": {"x":0,"y":0}
},
"plasma-2-0011.png":
{
	"frame": {"x":413,"y":37,"w":16,"h":16},
	"rotated": false,
	"trimmed": false,
	"spriteSourceSize": {"x":0,"y":0,"w":16,"h":16},
	"sourceSize": {"w":16,"h":16},
	"anchor": {"x":0,"y":0}
},
"plasma-2-0100.png":
{
	"frame": {"x":449,"y":19,"w":16,"h":16},
	"rotated": false,
	"trimmed": false,
	"spriteSourceSize": {"x":0,"y":0,"w":16,"h":16},
	"sourceSize": {"w":16,"h":16},
	"anchor": {"x":0,"y":0}
},
"plasma-2-0101.png":
{
	"frame": {"x":521,"y":91,"w":16,"h":14},
	"rotated": false,
	"trimmed": true,
	"spriteSourceSize": {"x":0,"y":0,"w":16,"h":14},
	"sourceSize": {"w":16,"h":16},
	"anchor": {"x":0,"y":0}
},
"plasma-2-0110.png":
{
	"frame": {"x":431,"y":37,"w":16,"h":16},
	"rotated": false,
	"trimmed": false,
	"spriteSourceSize": {"x":0,"y":0,"w":16,"h":16},
	"sourceSize": {"w":16,"h":16},
	"anchor": {"x":0,"y":0}
},
"plasma-2-0111.png":
{
	"frame": {"x":467,"y":19,"w":16,"h":16},
	"rotated": false,
	"trimmed": false,
	"spriteSourceSize": {"x":0,"y":0,"w":16,"h":16},
	"sourceSize": {"w":16,"h":16},
	"anchor": {"x":0,"y":0}
},
"plasma-2-1000.png":
{
	"frame": {"x":449,"y":37,"w":16,"h":16},
	"rotated": false,
	"trimmed": false,
	"spriteSourceSize": {"x":0,"y":0,"w":16,"h":16},
	"sourceSize": {"w":16,"h":16},
	"anchor": {"x":0,"y":0}
},
"plasma-2-1001.png":
{
	"frame": {"x":485,"y":19,"w":16,"h":16},
	"rotated": false,
	"trimmed": false,
	"spriteSourceSize": {"x":0,"y":0,"w":16,"h":16},
	"sourceSize": {"w":16,"h":16},
	"anchor": {"x":0,"y":0}
},
"plasma-2-1010.png":
{
	"frame": {"x":590,"y":109,"w":13,"h":16},
	"rotated": false,
	"trimmed": true,
	"spriteSourceSize": {"x":2,"y":0,"w":13,"h":16},
	"sourceSize": {"w":16,"h":16},
	"anchor": {"x":0,"y":0}
},
"plasma-2-1011.png":
{
	"frame": {"x":467,"y":37,"w":16,"h":16},
	"rotated": false,
	"trimmed": false,
	"spriteSourceSize": {"x":0,"y":0,"w":16,"h":16},
	"sourceSize": {"w":16,"h":16},
	"anchor": {"x":0,"y":0}
},
"plasma-2-1100.png":
{
	"frame": {"x":503,"y":19,"w":16,"h":16},
	"rotated": false,
	"trimmed": false,
	"spriteSourceSize": {"x":0,"y":0,"w":16,"h":16},
	"sourceSize": {"w":16,"h":16},
	"anchor": {"x":0,"y":0}
},
"plasma-2-1101.png":
{
	"frame": {"x":485,"y":37,"w":16,"h":16},
	"rotated": false,
	"trimmed": false,
	"spriteSourceSize": {"x":0,"y":0,"w":16,"h":16},
	"sourceSize": {"w":16,"h":16},
	"anchor": {"x":0,"y":0}
},
"plasma-2-1110.png":
{
	"frame": {"x":521,"y":19,"w":16,"h":16},
	"rotated": false,
	"trimmed": false,
	"spriteSourceSize": {"x":0,"y":0,"w":16,"h":16},
	"sourceSize": {"w":16,"h":16},
	"anchor": {"x":0,"y":0}
},
"plasma-2-1111.png":
{
	"frame": {"x":503,"y":37,"w":16,"h":16},
	"rotated": false,
	"trimmed": false,
	"spriteSourceSize": {"x":0,"y":0,"w":16,"h":16},
	"sourceSize": {"w":16,"h":16},
	"anchor": {"x":0,"y":0}
},
"plasma-3-0000.png":
{
	"frame": {"x":539,"y":19,"w":16,"h":16},
	"rotated": false,
	"trimmed": false,
	"spriteSourceSize": {"x":0,"y":0,"w":16,"h":16},
	"sourceSize": {"w":16,"h":16},
	"anchor": {"x":0,"y":0}
},
"plasma-3-0001.png":
{
	"frame": {"x":521,"y":37,"w":16,"h":16},
	"rotated": false,
	"trimmed": false,
	"spriteSourceSize": {"x":0,"y":0,"w":16,"h":16},
	"sourceSize": {"w":16,"h":16},
	"anchor": {"x":0,"y":0}
},
"plasma-3-0010.png":
{
	"frame": {"x":557,"y":19,"w":16,"h":16},
	"rotated": false,
	"trimmed": false,
	"spriteSourceSize": {"x":0,"y":0,"w":16,"h":16},
	"sourceSize": {"w":16,"h":16},
	"anchor": {"x":0,"y":0}
},
"plasma-3-0011.png":
{
	"frame": {"x":539,"y":37,"w":16,"h":16},
	"rotated": false,
	"trimmed": false,
	"spriteSourceSize": {"x":0,"y":0,"w":16,"h":16},
	"sourceSize": {"w":16,"h":16},
	"anchor": {"x":0,"y":0}
},
"plasma-3-0100.png":
{
	"frame": {"x":575,"y":19,"w":16,"h":16},
	"rotated": false,
	"trimmed": false,
	"spriteSourceSize": {"x":0,"y":0,"w":16,"h":16},
	"sourceSize": {"w":16,"h":16},
	"anchor": {"x":0,"y":0}
},
"plasma-3-0101.png":
{
	"frame": {"x":521,"y":107,"w":16,"h":14},
	"rotated": false,
	"trimmed": true,
	"spriteSourceSize": {"x":0,"y":0,"w":16,"h":14},
	"sourceSize": {"w":16,"h":16},
	"anchor": {"x":0,"y":0}
},
"plasma-3-0110.png":
{
	"frame": {"x":557,"y":37,"w":16,"h":16},
	"rotated": false,
	"trimmed": false,
	"spriteSourceSize": {"x":0,"y":0,"w":16,"h":16},
	"sourceSize": {"w":16,"h":16},
	"anchor": {"x":0,"y":0}
},
"plasma-3-0111.png":
{
	"frame": {"x":593,"y":19,"w":16,"h":16},
	"rotated": false,
	"trimmed": false,
	"spriteSourceSize": {"x":0,"y":0,"w":16,"h":16},
	"sourceSize": {"w":16,"h":16},
	"anchor": {"x":0,"y":0}
},
"plasma-3-1000.png":
{
	"frame": {"x":575,"y":37,"w":16,"h":16},
	"rotated": false,
	"trimmed": false,
	"spriteSourceSize": {"x":0,"y":0,"w":16,"h":16},
	"sourceSize": {"w":16,"h":16},
	"anchor": {"x":0,"y":0}
},
"plasma-3-1001.png":
{
	"frame": {"x":611,"y":19,"w":16,"h":16},
	"rotated": false,
	"trimmed": false,
	"spriteSourceSize": {"x":0,"y":0,"w":16,"h":16},
	"sourceSize": {"w":16,"h":16},
	"anchor": {"x":0,"y":0}
},
"plasma-3-1010.png":
{
	"frame": {"x":605,"y":91,"w":13,"h":16},
	"rotated": false,
	"trimmed": true,
	"spriteSourceSize": {"x":1,"y":0,"w":13,"h":16},
	"sourceSize": {"w":16,"h":16},
	"anchor": {"x":0,"y":0}
},
"plasma-3-1011.png":
{
	"frame": {"x":593,"y":37,"w":16,"h":16},
	"rotated": false,
	"trimmed": false,
	"spriteSourceSize": {"x":0,"y":0,"w":16,"h":16},
	"sourceSize": {"w":16,"h":16},
	"anchor": {"x":0,"y":0}
},
"plasma-3-1100.png":
{
	"frame": {"x":629,"y":19,"w":16,"h":16},
	"rotated": false,
	"trimmed": false,
	"spriteSourceSize": {"x":0,"y":0,"w":16,"h":16},
	"sourceSize": {"w":16,"h":16},
	"anchor": {"x":0,"y":0}
},
"plasma-3-1101.png":
{
	"frame": {"x":611,"y":37,"w":16,"h":16},
	"rotated": false,
	"trimmed": false,
	"spriteSourceSize": {"x":0,"y":0,"w":16,"h":16},
	"sourceSize": {"w":16,"h":16},
	"anchor": {"x":0,"y":0}
},
"plasma-3-1110.png":
{
	"frame": {"x":647,"y":19,"w":16,"h":16},
	"rotated": false,
	"trimmed": false,
	"spriteSourceSize": {"x":0,"y":0,"w":16,"h":16},
	"sourceSize": {"w":16,"h":16},
	"anchor": {"x":0,"y":0}
},
"plasma-3-1111.png":
{
	"frame": {"x":629,"y":37,"w":16,"h":16},
	"rotated": false,
	"trimmed": false,
	"spriteSourceSize": {"x":0,"y":0,"w":16,"h":16},
	"sourceSize": {"w":16,"h":16},
	"anchor": {"x":0,"y":0}
},
"plasma.png":
{
	"frame": {"x":179,"y":26,"w":16,"h":17},
	"rotated": false,
	"trimmed": true,
	"spriteSourceSize": {"x":0,"y":15,"w":16,"h":17},
	"sourceSize": {"w":16,"h":32},
	"anchor": {"x":0,"y":0.5}
},
"port-white.png":
{
	"frame": {"x":251,"y":1,"w":16,"h":21},
	"rotated": false,
	"trimmed": true,
	"spriteSourceSize": {"x":0,"y":11,"w":16,"h":21},
	"sourceSize": {"w":16,"h":32},
	"anchor": {"x":0,"y":0.5}
},
"port.png":
{
	"frame": {"x":269,"y":1,"w":16,"h":21},
	"rotated": false,
	"trimmed": true,
	"spriteSourceSize": {"x":0,"y":11,"w":16,"h":21},
	"sourceSize": {"w":16,"h":32},
	"anchor": {"x":0,"y":0.5}
},
"radar-white.png":
{
	"frame": {"x":72,"y":32,"w":15,"h":19},
	"rotated": false,
	"trimmed": true,
	"spriteSourceSize": {"x":1,"y":13,"w":15,"h":19},
	"sourceSize": {"w":16,"h":32},
	"anchor": {"x":0,"y":0.5}
},
"radar.png":
{
	"frame": {"x":89,"y":29,"w":16,"h":19},
	"rotated": false,
	"trimmed": true,
	"spriteSourceSize": {"x":0,"y":13,"w":16,"h":19},
	"sourceSize": {"w":16,"h":32},
	"anchor": {"x":0,"y":0.5}
},
"reef-0.png":
{
	"frame": {"x":665,"y":19,"w":16,"h":16},
	"rotated": false,
	"trimmed": false,
	"spriteSourceSize": {"x":0,"y":0,"w":16,"h":16},
	"sourceSize": {"w":16,"h":16},
	"anchor": {"x":0,"y":0}
},
"reef-1.png":
{
	"frame": {"x":647,"y":37,"w":16,"h":16},
	"rotated": false,
	"trimmed": false,
	"spriteSourceSize": {"x":0,"y":0,"w":16,"h":16},
	"sourceSize": {"w":16,"h":16},
	"anchor": {"x":0,"y":0}
},
"reef-2.png":
{
	"frame": {"x":683,"y":19,"w":16,"h":16},
	"rotated": false,
	"trimmed": false,
	"spriteSourceSize": {"x":0,"y":0,"w":16,"h":16},
	"sourceSize": {"w":16,"h":16},
	"anchor": {"x":0,"y":0}
},
"reef-3.png":
{
	"frame": {"x":665,"y":37,"w":16,"h":16},
	"rotated": false,
	"trimmed": false,
	"spriteSourceSize": {"x":0,"y":0,"w":16,"h":16},
	"sourceSize": {"w":16,"h":16},
	"anchor": {"x":0,"y":0}
},
"reef.png":
{
	"frame": {"x":197,"y":25,"w":16,"h":17},
	"rotated": false,
	"trimmed": true,
	"spriteSourceSize": {"x":0,"y":15,"w":16,"h":17},
	"sourceSize": {"w":16,"h":32},
	"anchor": {"x":0,"y":0.5}
},
"river-0000.png":
{
	"frame": {"x":701,"y":19,"w":16,"h":16},
	"rotated": false,
	"trimmed": false,
	"spriteSourceSize": {"x":0,"y":0,"w":16,"h":16},
	"sourceSize": {"w":16,"h":16},
	"anchor": {"x":0,"y":0}
},
"river-0001.png":
{
	"frame": {"x":683,"y":37,"w":16,"h":16},
	"rotated": false,
	"trimmed": false,
	"spriteSourceSize": {"x":0,"y":0,"w":16,"h":16},
	"sourceSize": {"w":16,"h":16},
	"anchor": {"x":0,"y":0}
},
"river-0010.png":
{
	"frame": {"x":719,"y":19,"w":16,"h":16},
	"rotated": false,
	"trimmed": false,
	"spriteSourceSize": {"x":0,"y":0,"w":16,"h":16},
	"sourceSize": {"w":16,"h":16},
	"anchor": {"x":0,"y":0}
},
"river-0011.png":
{
	"frame": {"x":701,"y":37,"w":16,"h":16},
	"rotated": false,
	"trimmed": false,
	"spriteSourceSize": {"x":0,"y":0,"w":16,"h":16},
	"sourceSize": {"w":16,"h":16},
	"anchor": {"x":0,"y":0}
},
"river-0100.png":
{
	"frame": {"x":737,"y":19,"w":16,"h":16},
	"rotated": false,
	"trimmed": false,
	"spriteSourceSize": {"x":0,"y":0,"w":16,"h":16},
	"sourceSize": {"w":16,"h":16},
	"anchor": {"x":0,"y":0}
},
"river-0101.png":
{
	"frame": {"x":719,"y":37,"w":16,"h":16},
	"rotated": false,
	"trimmed": false,
	"spriteSourceSize": {"x":0,"y":0,"w":16,"h":16},
	"sourceSize": {"w":16,"h":16},
	"anchor": {"x":0,"y":0}
},
"river-0110.png":
{
	"frame": {"x":755,"y":19,"w":16,"h":16},
	"rotated": false,
	"trimmed": false,
	"spriteSourceSize": {"x":0,"y":0,"w":16,"h":16},
	"sourceSize": {"w":16,"h":16},
	"anchor": {"x":0,"y":0}
},
"river-0111.png":
{
	"frame": {"x":737,"y":37,"w":16,"h":16},
	"rotated": false,
	"trimmed": false,
	"spriteSourceSize": {"x":0,"y":0,"w":16,"h":16},
	"sourceSize": {"w":16,"h":16},
	"anchor": {"x":0,"y":0}
},
"river-1000.png":
{
	"frame": {"x":773,"y":19,"w":16,"h":16},
	"rotated": false,
	"trimmed": false,
	"spriteSourceSize": {"x":0,"y":0,"w":16,"h":16},
	"sourceSize": {"w":16,"h":16},
	"anchor": {"x":0,"y":0}
},
"river-1001.png":
{
	"frame": {"x":808,"y":23,"w":16,"h":16},
	"rotated": false,
	"trimmed": false,
	"spriteSourceSize": {"x":0,"y":0,"w":16,"h":16},
	"sourceSize": {"w":16,"h":16},
	"anchor": {"x":0,"y":0}
},
"river-1010.png":
{
	"frame": {"x":755,"y":37,"w":16,"h":16},
	"rotated": false,
	"trimmed": false,
	"spriteSourceSize": {"x":0,"y":0,"w":16,"h":16},
	"sourceSize": {"w":16,"h":16},
	"anchor": {"x":0,"y":0}
},
"river-1011.png":
{
	"frame": {"x":773,"y":37,"w":16,"h":16},
	"rotated": false,
	"trimmed": false,
	"spriteSourceSize": {"x":0,"y":0,"w":16,"h":16},
	"sourceSize": {"w":16,"h":16},
	"anchor": {"x":0,"y":0}
},
"river-1100.png":
{
	"frame": {"x":808,"y":41,"w":16,"h":16},
	"rotated": false,
	"trimmed": false,
	"spriteSourceSize": {"x":0,"y":0,"w":16,"h":16},
	"sourceSize": {"w":16,"h":16},
	"anchor": {"x":0,"y":0}
},
"river-1101.png":
{
	"frame": {"x":324,"y":55,"w":16,"h":16},
	"rotated": false,
	"trimmed": false,
	"spriteSourceSize": {"x":0,"y":0,"w":16,"h":16},
	"sourceSize": {"w":16,"h":16},
	"anchor": {"x":0,"y":0}
},
"river-1110.png":
{
	"frame": {"x":324,"y":73,"w":16,"h":16},
	"rotated": false,
	"trimmed": false,
	"spriteSourceSize": {"x":0,"y":0,"w":16,"h":16},
	"sourceSize": {"w":16,"h":16},
	"anchor": {"x":0,"y":0}
},
"river-1111.png":
{
	"frame": {"x":342,"y":55,"w":16,"h":16},
	"rotated": false,
	"trimmed": false,
	"spriteSourceSize": {"x":0,"y":0,"w":16,"h":16},
	"sourceSize": {"w":16,"h":16},
	"anchor": {"x":0,"y":0}
},
"river.png":
{
	"frame": {"x":215,"y":25,"w":16,"h":17},
	"rotated": false,
	"trimmed": true,
	"spriteSourceSize": {"x":0,"y":15,"w":16,"h":17},
	"sourceSize": {"w":16,"h":32},
	"anchor": {"x":0,"y":0.5}
},
"road-0000.png":
{
	"frame": {"x":760,"y":106,"w":14,"h":8},
	"rotated": false,
	"trimmed": true,
	"spriteSourceSize": {"x":1,"y":4,"w":14,"h":8},
	"sourceSize": {"w":16,"h":16},
	"anchor": {"x":0,"y":0}
},
"road-0001.png":
{
	"frame": {"x":733,"y":117,"w":15,"h":8},
	"rotated": false,
	"trimmed": true,
	"spriteSourceSize": {"x":0,"y":4,"w":15,"h":8},
	"sourceSize": {"w":16,"h":16},
	"anchor": {"x":0,"y":0}
},
"road-0010.png":
{
	"frame": {"x":217,"y":116,"w":8,"h":16},
	"rotated": true,
	"trimmed": true,
	"spriteSourceSize": {"x":4,"y":0,"w":8,"h":16},
	"sourceSize": {"w":16,"h":16},
	"anchor": {"x":0,"y":0}
},
"road-0011.png":
{
	"frame": {"x":715,"y":103,"w":12,"h":12},
	"rotated": false,
	"trimmed": true,
	"spriteSourceSize": {"x":0,"y":4,"w":12,"h":12},
	"sourceSize": {"w":16,"h":16},
	"anchor": {"x":0,"y":0}
},
"road-0100.png":
{
	"frame": {"x":743,"y":106,"w":15,"h":8},
	"rotated": false,
	"trimmed": true,
	"spriteSourceSize": {"x":1,"y":4,"w":15,"h":8},
	"sourceSize": {"w":16,"h":16},
	"anchor": {"x":0,"y":0}
},
"road-0101.png":
{
	"frame": {"x":181,"y":117,"w":16,"h":8},
	"rotated": false,
	"trimmed": true,
	"spriteSourceSize": {"x":0,"y":4,"w":16,"h":8},
	"sourceSize": {"w":16,"h":16},
	"anchor": {"x":0,"y":0}
},
"road-0110.png":
{
	"frame": {"x":729,"y":103,"w":12,"h":12},
	"rotated": false,
	"trimmed": true,
	"spriteSourceSize": {"x":4,"y":4,"w":12,"h":12},
	"sourceSize": {"w":16,"h":16},
	"anchor": {"x":0,"y":0}
},
"road-0111.png":
{
	"frame": {"x":662,"y":91,"w":16,"h":12},
	"rotated": false,
	"trimmed": true,
	"spriteSourceSize": {"x":0,"y":4,"w":16,"h":12},
	"sourceSize": {"w":16,"h":16},
	"anchor": {"x":0,"y":0}
},
"road-1000.png":
{
	"frame": {"x":808,"y":95,"w":8,"h":16},
	"rotated": true,
	"trimmed": true,
	"spriteSourceSize": {"x":4,"y":0,"w":8,"h":16},
	"sourceSize": {"w":16,"h":16},
	"anchor": {"x":0,"y":0}
},
"road-1001.png":
{
	"frame": {"x":776,"y":113,"w":12,"h":12},
	"rotated": false,
	"trimmed": true,
	"spriteSourceSize": {"x":0,"y":0,"w":12,"h":12},
	"sourceSize": {"w":16,"h":16},
	"anchor": {"x":0,"y":0}
},
"road-1010.png":
{
	"frame": {"x":808,"y":105,"w":8,"h":16},
	"rotated": true,
	"trimmed": true,
	"spriteSourceSize": {"x":4,"y":0,"w":8,"h":16},
	"sourceSize": {"w":16,"h":16},
	"anchor": {"x":0,"y":0}
},
"road-1011.png":
{
	"frame": {"x":662,"y":105,"w":12,"h":16},
	"rotated": false,
	"trimmed": true,
	"spriteSourceSize": {"x":0,"y":0,"w":12,"h":16},
	"sourceSize": {"w":16,"h":16},
	"anchor": {"x":0,"y":0}
},
"road-1100.png":
{
	"frame": {"x":790,"y":113,"w":12,"h":12},
	"rotated": false,
	"trimmed": true,
	"spriteSourceSize": {"x":4,"y":0,"w":12,"h":12},
	"sourceSize": {"w":16,"h":16},
	"anchor": {"x":0,"y":0}
},
"road-1101.png":
{
	"frame": {"x":680,"y":91,"w":16,"h":12},
	"rotated": false,
	"trimmed": true,
	"spriteSourceSize": {"x":0,"y":0,"w":16,"h":12},
	"sourceSize": {"w":16,"h":16},
	"anchor": {"x":0,"y":0}
},
"road-1110.png":
{
	"frame": {"x":676,"y":105,"w":12,"h":16},
	"rotated": false,
	"trimmed": true,
	"spriteSourceSize": {"x":4,"y":0,"w":12,"h":16},
	"sourceSize": {"w":16,"h":16},
	"anchor": {"x":0,"y":0}
},
"road-1111.png":
{
	"frame": {"x":342,"y":73,"w":16,"h":16},
	"rotated": false,
	"trimmed": false,
	"spriteSourceSize": {"x":0,"y":0,"w":16,"h":16},
	"sourceSize": {"w":16,"h":16},
	"anchor": {"x":0,"y":0}
},
"road.png":
{
	"frame": {"x":233,"y":24,"w":16,"h":17},
	"rotated": false,
	"trimmed": true,
	"spriteSourceSize": {"x":0,"y":15,"w":16,"h":17},
	"sourceSize": {"w":16,"h":32},
	"anchor": {"x":0,"y":0.5}
},
"rough-0.png":
{
	"frame": {"x":360,"y":55,"w":16,"h":16},
	"rotated": false,
	"trimmed": false,
	"spriteSourceSize": {"x":0,"y":0,"w":16,"h":16},
	"sourceSize": {"w":16,"h":16},
	"anchor": {"x":0,"y":0}
},
"rough-1.png":
{
	"frame": {"x":539,"y":91,"w":16,"h":14},
	"rotated": false,
	"trimmed": true,
	"spriteSourceSize": {"x":0,"y":2,"w":16,"h":14},
	"sourceSize": {"w":16,"h":16},
	"anchor": {"x":0,"y":0}
},
"rough-2.png":
{
	"frame": {"x":539,"y":107,"w":16,"h":14},
	"rotated": false,
	"trimmed": true,
	"spriteSourceSize": {"x":0,"y":2,"w":16,"h":14},
	"sourceSize": {"w":16,"h":16},
	"anchor": {"x":0,"y":0}
},
"rough-3.png":
{
	"frame": {"x":557,"y":91,"w":16,"h":14},
	"rotated": false,
	"trimmed": true,
	"spriteSourceSize": {"x":0,"y":2,"w":16,"h":14},
	"sourceSize": {"w":16,"h":16},
	"anchor": {"x":0,"y":0}
},
"rough-4.png":
{
	"frame": {"x":469,"y":109,"w":16,"h":15},
	"rotated": true,
	"trimmed": true,
	"spriteSourceSize": {"x":0,"y":1,"w":16,"h":15},
	"sourceSize": {"w":16,"h":16},
	"anchor": {"x":0,"y":0}
},
"rough.png":
{
	"frame": {"x":251,"y":24,"w":16,"h":17},
	"rotated": false,
	"trimmed": true,
	"spriteSourceSize": {"x":0,"y":15,"w":16,"h":17},
	"sourceSize": {"w":16,"h":32},
	"anchor": {"x":0,"y":0.5}
},
"ruins-0.png":
{
	"frame": {"x":360,"y":73,"w":16,"h":16},
	"rotated": false,
	"trimmed": false,
	"spriteSourceSize": {"x":0,"y":0,"w":16,"h":16},
	"sourceSize": {"w":16,"h":16},
	"anchor": {"x":0,"y":0}
},
"ruins-1.png":
{
	"frame": {"x":378,"y":55,"w":16,"h":16},
	"rotated": false,
	"trimmed": false,
	"spriteSourceSize": {"x":0,"y":0,"w":16,"h":16},
	"sourceSize": {"w":16,"h":16},
	"anchor": {"x":0,"y":0}
},
"ruins-2.png":
{
	"frame": {"x":378,"y":73,"w":16,"h":16},
	"rotated": false,
	"trimmed": false,
	"spriteSourceSize": {"x":0,"y":0,"w":16,"h":16},
	"sourceSize": {"w":16,"h":16},
	"anchor": {"x":0,"y":0}
},
"ruins.png":
{
	"frame": {"x":269,"y":24,"w":16,"h":17},
	"rotated": false,
	"trimmed": true,
	"spriteSourceSize": {"x":0,"y":15,"w":16,"h":17},
	"sourceSize": {"w":16,"h":32},
	"anchor": {"x":0,"y":0.5}
},
"sea-0.png":
{
	"frame": {"x":396,"y":55,"w":16,"h":16},
	"rotated": false,
	"trimmed": false,
	"spriteSourceSize": {"x":0,"y":0,"w":16,"h":16},
	"sourceSize": {"w":16,"h":16},
	"anchor": {"x":0,"y":0}
},
"sea-1.png":
{
	"frame": {"x":396,"y":73,"w":16,"h":16},
	"rotated": false,
	"trimmed": false,
	"spriteSourceSize": {"x":0,"y":0,"w":16,"h":16},
	"sourceSize": {"w":16,"h":16},
	"anchor": {"x":0,"y":0}
},
"sea-2.png":
{
	"frame": {"x":414,"y":55,"w":16,"h":16},
	"rotated": false,
	"trimmed": false,
	"spriteSourceSize": {"x":0,"y":0,"w":16,"h":16},
	"sourceSize": {"w":16,"h":16},
	"anchor": {"x":0,"y":0}
},
"sea-3.png":
{
	"frame": {"x":414,"y":73,"w":16,"h":16},
	"rotated": false,
	"trimmed": false,
	"spriteSourceSize": {"x":0,"y":0,"w":16,"h":16},
	"sourceSize": {"w":16,"h":16},
	"anchor": {"x":0,"y":0}
},
"sea-4.png":
{
	"frame": {"x":432,"y":55,"w":16,"h":16},
	"rotated": false,
	"trimmed": false,
	"spriteSourceSize": {"x":0,"y":0,"w":16,"h":16},
	"sourceSize": {"w":16,"h":16},
	"anchor": {"x":0,"y":0}
},
"sea-cliff-0001.png":
{
	"frame": {"x":690,"y":105,"w":8,"h":16},
	"rotated": false,
	"trimmed": true,
	"spriteSourceSize": {"x":0,"y":0,"w":8,"h":16},
	"sourceSize": {"w":16,"h":16},
	"anchor": {"x":0,"y":0}
},
"sea-cliff-0002.png":
{
	"frame": {"x":750,"y":116,"w":6,"h":8},
	"rotated": false,
	"trimmed": true,
	"spriteSourceSize": {"x":0,"y":0,"w":6,"h":8},
	"sourceSize": {"w":16,"h":16},
	"anchor": {"x":0,"y":0}
},
"sea-cliff-0003.png":
{
	"frame": {"x":163,"y":118,"w":7,"h":16},
	"rotated": true,
	"trimmed": true,
	"spriteSourceSize": {"x":0,"y":0,"w":7,"h":16},
	"sourceSize": {"w":16,"h":16},
	"anchor": {"x":0,"y":0}
},
"sea-cliff-0010.png":
{
	"frame": {"x":127,"y":120,"w":16,"h":5},
	"rotated": false,
	"trimmed": true,
	"spriteSourceSize": {"x":0,"y":11,"w":16,"h":5},
	"sourceSize": {"w":16,"h":16},
	"anchor": {"x":0,"y":0}
},
"sea-cliff-0011.png":
{
	"frame": {"x":432,"y":73,"w":16,"h":16},
	"rotated": false,
	"trimmed": false,
	"spriteSourceSize": {"x":0,"y":0,"w":16,"h":16},
	"sourceSize": {"w":16,"h":16},
	"anchor": {"x":0,"y":0}
},
"sea-cliff-0012.png":
{
	"frame": {"x":450,"y":55,"w":16,"h":16},
	"rotated": false,
	"trimmed": false,
	"spriteSourceSize": {"x":0,"y":0,"w":16,"h":16},
	"sourceSize": {"w":16,"h":16},
	"anchor": {"x":0,"y":0}
},
"sea-cliff-0020.png":
{
	"frame": {"x":766,"y":116,"w":4,"h":4},
	"rotated": false,
	"trimmed": true,
	"spriteSourceSize": {"x":0,"y":12,"w":4,"h":4},
	"sourceSize": {"w":16,"h":16},
	"anchor": {"x":0,"y":0}
},
"sea-cliff-0022.png":
{
	"frame": {"x":776,"y":106,"w":5,"h":16},
	"rotated": true,
	"trimmed": true,
	"spriteSourceSize": {"x":0,"y":0,"w":5,"h":16},
	"sourceSize": {"w":16,"h":16},
	"anchor": {"x":0,"y":0}
},
"sea-cliff-0030.png":
{
	"frame": {"x":145,"y":119,"w":16,"h":5},
	"rotated": false,
	"trimmed": true,
	"spriteSourceSize": {"x":0,"y":11,"w":16,"h":5},
	"sourceSize": {"w":16,"h":16},
	"anchor": {"x":0,"y":0}
},
"sea-cliff-0100.png":
{
	"frame": {"x":715,"y":117,"w":8,"h":16},
	"rotated": true,
	"trimmed": true,
	"spriteSourceSize": {"x":8,"y":0,"w":8,"h":16},
	"sourceSize": {"w":16,"h":16},
	"anchor": {"x":0,"y":0}
},
"sea-cliff-0101.png":
{
	"frame": {"x":450,"y":73,"w":16,"h":16},
	"rotated": false,
	"trimmed": false,
	"spriteSourceSize": {"x":0,"y":0,"w":16,"h":16},
	"sourceSize": {"w":16,"h":16},
	"anchor": {"x":0,"y":0}
},
"sea-cliff-0102.png":
{
	"frame": {"x":468,"y":55,"w":16,"h":16},
	"rotated": false,
	"trimmed": false,
	"spriteSourceSize": {"x":0,"y":0,"w":16,"h":16},
	"sourceSize": {"w":16,"h":16},
	"anchor": {"x":0,"y":0}
},
"sea-cliff-0110.png":
{
	"frame": {"x":468,"y":73,"w":16,"h":16},
	"rotated": false,
	"trimmed": false,
	"spriteSourceSize": {"x":0,"y":0,"w":16,"h":16},
	"sourceSize": {"w":16,"h":16},
	"anchor": {"x":0,"y":0}
},
"sea-cliff-0111.png":
{
	"frame": {"x":486,"y":55,"w":16,"h":16},
	"rotated": false,
	"trimmed": false,
	"spriteSourceSize": {"x":0,"y":0,"w":16,"h":16},
	"sourceSize": {"w":16,"h":16},
	"anchor": {"x":0,"y":0}
},
"sea-cliff-0112.png":
{
	"frame": {"x":486,"y":73,"w":16,"h":16},
	"rotated": false,
	"trimmed": false,
	"spriteSourceSize": {"x":0,"y":0,"w":16,"h":16},
	"sourceSize": {"w":16,"h":16},
	"anchor": {"x":0,"y":0}
},
"sea-cliff-0120.png":
{
	"frame": {"x":504,"y":55,"w":16,"h":16},
	"rotated": false,
	"trimmed": false,
	"spriteSourceSize": {"x":0,"y":0,"w":16,"h":16},
	"sourceSize": {"w":16,"h":16},
	"anchor": {"x":0,"y":0}
},
"sea-cliff-0122.png":
{
	"frame": {"x":504,"y":73,"w":16,"h":16},
	"rotated": false,
	"trimmed": false,
	"spriteSourceSize": {"x":0,"y":0,"w":16,"h":16},
	"sourceSize": {"w":16,"h":16},
	"anchor": {"x":0,"y":0}
},
"sea-cliff-0200.png":
{
	"frame": {"x":758,"y":116,"w":6,"h":4},
	"rotated": false,
	"trimmed": true,
	"spriteSourceSize": {"x":10,"y":12,"w":6,"h":4},
	"sourceSize": {"w":16,"h":16},
	"anchor": {"x":0,"y":0}
},
"sea-cliff-0201.png":
{
	"frame": {"x":522,"y":55,"w":16,"h":16},
	"rotated": false,
	"trimmed": false,
	"spriteSourceSize": {"x":0,"y":0,"w":16,"h":16},
	"sourceSize": {"w":16,"h":16},
	"anchor": {"x":0,"y":0}
},
"sea-cliff-0202.png":
{
	"frame": {"x":522,"y":73,"w":16,"h":16},
	"rotated": false,
	"trimmed": false,
	"spriteSourceSize": {"x":0,"y":0,"w":16,"h":16},
	"sourceSize": {"w":16,"h":16},
	"anchor": {"x":0,"y":0}
},
"sea-cliff-0220.png":
{
	"frame": {"x":109,"y":121,"w":16,"h":4},
	"rotated": false,
	"trimmed": true,
	"spriteSourceSize": {"x":0,"y":12,"w":16,"h":4},
	"sourceSize": {"w":16,"h":16},
	"anchor": {"x":0,"y":0}
},
"sea-cliff-0222.png":
{
	"frame": {"x":540,"y":55,"w":16,"h":16},
	"rotated": false,
	"trimmed": false,
	"spriteSourceSize": {"x":0,"y":0,"w":16,"h":16},
	"sourceSize": {"w":16,"h":16},
	"anchor": {"x":0,"y":0}
},
"sea-cliff-0300.png":
{
	"frame": {"x":37,"y":119,"w":6,"h":16},
	"rotated": true,
	"trimmed": true,
	"spriteSourceSize": {"x":10,"y":0,"w":6,"h":16},
	"sourceSize": {"w":16,"h":16},
	"anchor": {"x":0,"y":0}
},
"sea-cliff-1000.png":
{
	"frame": {"x":698,"y":91,"w":16,"h":10},
	"rotated": false,
	"trimmed": true,
	"spriteSourceSize": {"x":0,"y":0,"w":16,"h":10},
	"sourceSize": {"w":16,"h":16},
	"anchor": {"x":0,"y":0}
},
"sea-cliff-1001.png":
{
	"frame": {"x":540,"y":73,"w":16,"h":16},
	"rotated": false,
	"trimmed": false,
	"spriteSourceSize": {"x":0,"y":0,"w":16,"h":16},
	"sourceSize": {"w":16,"h":16},
	"anchor": {"x":0,"y":0}
},
"sea-cliff-1010.png":
{
	"frame": {"x":558,"y":55,"w":16,"h":16},
	"rotated": false,
	"trimmed": false,
	"spriteSourceSize": {"x":0,"y":0,"w":16,"h":16},
	"sourceSize": {"w":16,"h":16},
	"anchor": {"x":0,"y":0}
},
"sea-cliff-1011.png":
{
	"frame": {"x":558,"y":73,"w":16,"h":16},
	"rotated": false,
	"trimmed": false,
	"spriteSourceSize": {"x":0,"y":0,"w":16,"h":16},
	"sourceSize": {"w":16,"h":16},
	"anchor": {"x":0,"y":0}
},
"sea-cliff-1020.png":
{
	"frame": {"x":576,"y":55,"w":16,"h":16},
	"rotated": false,
	"trimmed": false,
	"spriteSourceSize": {"x":0,"y":0,"w":16,"h":16},
	"sourceSize": {"w":16,"h":16},
	"anchor": {"x":0,"y":0}
},
"sea-cliff-1100.png":
{
	"frame": {"x":576,"y":73,"w":16,"h":16},
	"rotated": false,
	"trimmed": false,
	"spriteSourceSize": {"x":0,"y":0,"w":16,"h":16},
	"sourceSize": {"w":16,"h":16},
	"anchor": {"x":0,"y":0}
},
"sea-cliff-1101.png":
{
	"frame": {"x":594,"y":55,"w":16,"h":16},
	"rotated": false,
	"trimmed": false,
	"spriteSourceSize": {"x":0,"y":0,"w":16,"h":16},
	"sourceSize": {"w":16,"h":16},
	"anchor": {"x":0,"y":0}
},
"sea-cliff-1110.png":
{
	"frame": {"x":594,"y":73,"w":16,"h":16},
	"rotated": false,
	"trimmed": false,
	"spriteSourceSize": {"x":0,"y":0,"w":16,"h":16},
	"sourceSize": {"w":16,"h":16},
	"anchor": {"x":0,"y":0}
},
"sea-cliff-1111.png":
{
	"frame": {"x":612,"y":55,"w":16,"h":16},
	"rotated": false,
	"trimmed": false,
	"spriteSourceSize": {"x":0,"y":0,"w":16,"h":16},
	"sourceSize": {"w":16,"h":16},
	"anchor": {"x":0,"y":0}
},
"sea-cliff-1120.png":
{
	"frame": {"x":612,"y":73,"w":16,"h":16},
	"rotated": false,
	"trimmed": false,
	"spriteSourceSize": {"x":0,"y":0,"w":16,"h":16},
	"sourceSize": {"w":16,"h":16},
	"anchor": {"x":0,"y":0}
},
"sea-cliff-1200.png":
{
	"frame": {"x":630,"y":55,"w":16,"h":16},
	"rotated": false,
	"trimmed": false,
	"spriteSourceSize": {"x":0,"y":0,"w":16,"h":16},
	"sourceSize": {"w":16,"h":16},
	"anchor": {"x":0,"y":0}
},
"sea-cliff-1201.png":
{
	"frame": {"x":630,"y":73,"w":16,"h":16},
	"rotated": false,
	"trimmed": false,
	"spriteSourceSize": {"x":0,"y":0,"w":16,"h":16},
	"sourceSize": {"w":16,"h":16},
	"anchor": {"x":0,"y":0}
},
"sea-cliff-1220.png":
{
	"frame": {"x":648,"y":55,"w":16,"h":16},
	"rotated": false,
	"trimmed": false,
	"spriteSourceSize": {"x":0,"y":0,"w":16,"h":16},
	"sourceSize": {"w":16,"h":16},
	"anchor": {"x":0,"y":0}
},
"sea-cliff-2000.png":
{
	"frame": {"x":700,"y":118,"w":7,"h":9},
	"rotated": true,
	"trimmed": true,
	"spriteSourceSize": {"x":9,"y":0,"w":7,"h":9},
	"sourceSize": {"w":16,"h":16},
	"anchor": {"x":0,"y":0}
},
"sea-cliff-2001.png":
{
	"frame": {"x":648,"y":73,"w":16,"h":16},
	"rotated": false,
	"trimmed": false,
	"spriteSourceSize": {"x":0,"y":0,"w":16,"h":16},
	"sourceSize": {"w":16,"h":16},
	"anchor": {"x":0,"y":0}
},
"sea-cliff-2002.png":
{
	"frame": {"x":199,"y":116,"w":16,"h":9},
	"rotated": false,
	"trimmed": true,
	"spriteSourceSize": {"x":0,"y":0,"w":16,"h":9},
	"sourceSize": {"w":16,"h":16},
	"anchor": {"x":0,"y":0}
},
"sea-cliff-2010.png":
{
	"frame": {"x":666,"y":55,"w":16,"h":16},
	"rotated": false,
	"trimmed": false,
	"spriteSourceSize": {"x":0,"y":0,"w":16,"h":16},
	"sourceSize": {"w":16,"h":16},
	"anchor": {"x":0,"y":0}
},
"sea-cliff-2011.png":
{
	"frame": {"x":666,"y":73,"w":16,"h":16},
	"rotated": false,
	"trimmed": false,
	"spriteSourceSize": {"x":0,"y":0,"w":16,"h":16},
	"sourceSize": {"w":16,"h":16},
	"anchor": {"x":0,"y":0}
},
"sea-cliff-2012.png":
{
	"frame": {"x":684,"y":55,"w":16,"h":16},
	"rotated": false,
	"trimmed": false,
	"spriteSourceSize": {"x":0,"y":0,"w":16,"h":16},
	"sourceSize": {"w":16,"h":16},
	"anchor": {"x":0,"y":0}
},
"sea-cliff-2020.png":
{
	"frame": {"x":684,"y":73,"w":16,"h":16},
	"rotated": false,
	"trimmed": false,
	"spriteSourceSize": {"x":0,"y":0,"w":16,"h":16},
	"sourceSize": {"w":16,"h":16},
	"anchor": {"x":0,"y":0}
},
"sea-cliff-2022.png":
{
	"frame": {"x":702,"y":55,"w":16,"h":16},
	"rotated": false,
	"trimmed": false,
	"spriteSourceSize": {"x":0,"y":0,"w":16,"h":16},
	"sourceSize": {"w":16,"h":16},
	"anchor": {"x":0,"y":0}
},
"sea-cliff-2200.png":
{
	"frame": {"x":799,"y":91,"w":7,"h":16},
	"rotated": false,
	"trimmed": true,
	"spriteSourceSize": {"x":9,"y":0,"w":7,"h":16},
	"sourceSize": {"w":16,"h":16},
	"anchor": {"x":0,"y":0}
},
"sea-cliff-2201.png":
{
	"frame": {"x":702,"y":73,"w":16,"h":16},
	"rotated": false,
	"trimmed": false,
	"spriteSourceSize": {"x":0,"y":0,"w":16,"h":16},
	"sourceSize": {"w":16,"h":16},
	"anchor": {"x":0,"y":0}
},
"sea-cliff-2202.png":
{
	"frame": {"x":720,"y":55,"w":16,"h":16},
	"rotated": false,
	"trimmed": false,
	"spriteSourceSize": {"x":0,"y":0,"w":16,"h":16},
	"sourceSize": {"w":16,"h":16},
	"anchor": {"x":0,"y":0}
},
"sea-cliff-2220.png":
{
	"frame": {"x":720,"y":73,"w":16,"h":16},
	"rotated": false,
	"trimmed": false,
	"spriteSourceSize": {"x":0,"y":0,"w":16,"h":16},
	"sourceSize": {"w":16,"h":16},
	"anchor": {"x":0,"y":0}
},
"sea-cliff-2222.png":
{
	"frame": {"x":738,"y":55,"w":16,"h":16},
	"rotated": false,
	"trimmed": false,
	"spriteSourceSize": {"x":0,"y":0,"w":16,"h":16},
	"sourceSize": {"w":16,"h":16},
	"anchor": {"x":0,"y":0}
},
"sea-cliff-3000.png":
{
	"frame": {"x":716,"y":91,"w":16,"h":10},
	"rotated": false,
	"trimmed": true,
	"spriteSourceSize": {"x":0,"y":0,"w":16,"h":10},
	"sourceSize": {"w":16,"h":16},
	"anchor": {"x":0,"y":0}
},
"sea-shallow-0001.png":
{
	"frame": {"x":738,"y":73,"w":16,"h":16},
	"rotated": false,
	"trimmed": false,
	"spriteSourceSize": {"x":0,"y":0,"w":16,"h":16},
	"sourceSize": {"w":16,"h":16},
	"anchor": {"x":0,"y":0}
},
"sea-shallow-0010.png":
{
	"frame": {"x":756,"y":55,"w":16,"h":16},
	"rotated": false,
	"trimmed": false,
	"spriteSourceSize": {"x":0,"y":0,"w":16,"h":16},
	"sourceSize": {"w":16,"h":16},
	"anchor": {"x":0,"y":0}
},
"sea-shallow-0011.png":
{
	"frame": {"x":756,"y":73,"w":16,"h":16},
	"rotated": false,
	"trimmed": false,
	"spriteSourceSize": {"x":0,"y":0,"w":16,"h":16},
	"sourceSize": {"w":16,"h":16},
	"anchor": {"x":0,"y":0}
},
"sea-shallow-0100.png":
{
	"frame": {"x":774,"y":55,"w":16,"h":16},
	"rotated": false,
	"trimmed": false,
	"spriteSourceSize": {"x":0,"y":0,"w":16,"h":16},
	"sourceSize": {"w":16,"h":16},
	"anchor": {"x":0,"y":0}
},
"sea-shallow-0101.png":
{
	"frame": {"x":808,"y":59,"w":16,"h":16},
	"rotated": false,
	"trimmed": false,
	"spriteSourceSize": {"x":0,"y":0,"w":16,"h":16},
	"sourceSize": {"w":16,"h":16},
	"anchor": {"x":0,"y":0}
},
"sea-shallow-0110.png":
{
	"frame": {"x":774,"y":73,"w":16,"h":16},
	"rotated": false,
	"trimmed": false,
	"spriteSourceSize": {"x":0,"y":0,"w":16,"h":16},
	"sourceSize": {"w":16,"h":16},
	"anchor": {"x":0,"y":0}
},
"sea-shallow-0111.png":
{
	"frame": {"x":808,"y":77,"w":16,"h":16},
	"rotated": false,
	"trimmed": false,
	"spriteSourceSize": {"x":0,"y":0,"w":16,"h":16},
	"sourceSize": {"w":16,"h":16},
	"anchor": {"x":0,"y":0}
},
"sea-shallow-1000.png":
{
	"frame": {"x":325,"y":91,"w":16,"h":16},
	"rotated": false,
	"trimmed": false,
	"spriteSourceSize": {"x":0,"y":0,"w":16,"h":16},
	"sourceSize": {"w":16,"h":16},
	"anchor": {"x":0,"y":0}
},
"sea-shallow-1001.png":
{
	"frame": {"x":325,"y":109,"w":16,"h":16},
	"rotated": false,
	"trimmed": false,
	"spriteSourceSize": {"x":0,"y":0,"w":16,"h":16},
	"sourceSize": {"w":16,"h":16},
	"anchor": {"x":0,"y":0}
},
"sea-shallow-1010.png":
{
	"frame": {"x":343,"y":91,"w":16,"h":16},
	"rotated": false,
	"trimmed": false,
	"spriteSourceSize": {"x":0,"y":0,"w":16,"h":16},
	"sourceSize": {"w":16,"h":16},
	"anchor": {"x":0,"y":0}
},
"sea-shallow-1011.png":
{
	"frame": {"x":343,"y":109,"w":16,"h":16},
	"rotated": false,
	"trimmed": false,
	"spriteSourceSize": {"x":0,"y":0,"w":16,"h":16},
	"sourceSize": {"w":16,"h":16},
	"anchor": {"x":0,"y":0}
},
"sea-shallow-1100.png":
{
	"frame": {"x":361,"y":91,"w":16,"h":16},
	"rotated": false,
	"trimmed": false,
	"spriteSourceSize": {"x":0,"y":0,"w":16,"h":16},
	"sourceSize": {"w":16,"h":16},
	"anchor": {"x":0,"y":0}
},
"sea-shallow-1101.png":
{
	"frame": {"x":361,"y":109,"w":16,"h":16},
	"rotated": false,
	"trimmed": false,
	"spriteSourceSize": {"x":0,"y":0,"w":16,"h":16},
	"sourceSize": {"w":16,"h":16},
	"anchor": {"x":0,"y":0}
},
"sea-shallow-1110.png":
{
	"frame": {"x":379,"y":91,"w":16,"h":16},
	"rotated": false,
	"trimmed": false,
	"spriteSourceSize": {"x":0,"y":0,"w":16,"h":16},
	"sourceSize": {"w":16,"h":16},
	"anchor": {"x":0,"y":0}
},
"sea-shallow-1111.png":
{
	"frame": {"x":379,"y":109,"w":16,"h":16},
	"rotated": false,
	"trimmed": false,
	"spriteSourceSize": {"x":0,"y":0,"w":16,"h":16},
	"sourceSize": {"w":16,"h":16},
	"anchor": {"x":0,"y":0}
},
"sea.png":
{
	"frame": {"x":287,"y":23,"w":16,"h":17},
	"rotated": false,
	"trimmed": true,
	"spriteSourceSize": {"x":0,"y":15,"w":16,"h":17},
	"sourceSize": {"w":16,"h":32},
	"anchor": {"x":0,"y":0.5}
},
"shadow.png":
{
	"frame": {"x":1,"y":1,"w":32,"h":32},
	"rotated": false,
	"trimmed": false,
	"spriteSourceSize": {"x":0,"y":0,"w":32,"h":32},
	"sourceSize": {"w":32,"h":32},
	"anchor": {"x":0,"y":0}
},
"silo-1.png":
{
	"frame": {"x":37,"y":34,"w":15,"h":20},
	"rotated": false,
	"trimmed": true,
	"spriteSourceSize": {"x":1,"y":12,"w":15,"h":20},
	"sourceSize": {"w":16,"h":32},
	"anchor": {"x":0,"y":0.5}
},
"silo-2.png":
{
	"frame": {"x":55,"y":74,"w":15,"h":17},
	"rotated": false,
	"trimmed": true,
	"spriteSourceSize": {"x":1,"y":15,"w":15,"h":17},
	"sourceSize": {"w":16,"h":32},
	"anchor": {"x":0,"y":0.5}
},
"silo.png":
{
	"frame": {"x":19,"y":101,"w":16,"h":20},
	"rotated": false,
	"trimmed": true,
	"spriteSourceSize": {"x":0,"y":12,"w":16,"h":20},
	"sourceSize": {"w":16,"h":32},
	"anchor": {"x":0,"y":0.5}
},
"tair-white.png":
{
	"frame": {"x":305,"y":23,"w":16,"h":17},
	"rotated": false,
	"trimmed": true,
	"spriteSourceSize": {"x":0,"y":15,"w":16,"h":17},
	"sourceSize": {"w":16,"h":32},
	"anchor": {"x":0,"y":0.5}
},
"tair.png":
{
	"frame": {"x":323,"y":18,"w":16,"h":17},
	"rotated": false,
	"trimmed": true,
	"spriteSourceSize": {"x":0,"y":15,"w":16,"h":17},
	"sourceSize": {"w":16,"h":32},
	"anchor": {"x":0,"y":0.5}
},
"tport-white.png":
{
	"frame": {"x":89,"y":50,"w":16,"h":17},
	"rotated": false,
	"trimmed": true,
	"spriteSourceSize": {"x":0,"y":15,"w":16,"h":17},
	"sourceSize": {"w":16,"h":32},
	"anchor": {"x":0,"y":0.5}
},
"tport.png":
{
	"frame": {"x":107,"y":48,"w":16,"h":17},
	"rotated": false,
	"trimmed": true,
	"spriteSourceSize": {"x":0,"y":15,"w":16,"h":17},
	"sourceSize": {"w":16,"h":32},
	"anchor": {"x":0,"y":0.5}
},
"wasteland-0.png":
{
	"frame": {"x":397,"y":91,"w":16,"h":16},
	"rotated": false,
	"trimmed": false,
	"spriteSourceSize": {"x":0,"y":0,"w":16,"h":16},
	"sourceSize": {"w":16,"h":16},
	"anchor": {"x":0,"y":0}
},
"wasteland-1.png":
{
	"frame": {"x":397,"y":109,"w":16,"h":16},
	"rotated": false,
	"trimmed": false,
	"spriteSourceSize": {"x":0,"y":0,"w":16,"h":16},
	"sourceSize": {"w":16,"h":16},
	"anchor": {"x":0,"y":0}
},
"wasteland-2.png":
{
	"frame": {"x":415,"y":91,"w":16,"h":16},
	"rotated": false,
	"trimmed": false,
	"spriteSourceSize": {"x":0,"y":0,"w":16,"h":16},
	"sourceSize": {"w":16,"h":16},
	"anchor": {"x":0,"y":0}
},
"wasteland-3.png":
{
	"frame": {"x":415,"y":109,"w":16,"h":16},
	"rotated": false,
	"trimmed": false,
	"spriteSourceSize": {"x":0,"y":0,"w":16,"h":16},
	"sourceSize": {"w":16,"h":16},
	"anchor": {"x":0,"y":0}
},
"wasteland-4.png":
{
	"frame": {"x":433,"y":91,"w":16,"h":16},
	"rotated": false,
	"trimmed": false,
	"spriteSourceSize": {"x":0,"y":0,"w":16,"h":16},
	"sourceSize": {"w":16,"h":16},
	"anchor": {"x":0,"y":0}
},
"wasteland-5.png":
{
	"frame": {"x":433,"y":109,"w":16,"h":16},
	"rotated": false,
	"trimmed": false,
	"spriteSourceSize": {"x":0,"y":0,"w":16,"h":16},
	"sourceSize": {"w":16,"h":16},
	"anchor": {"x":0,"y":0}
},
"wasteland-6.png":
{
	"frame": {"x":451,"y":91,"w":16,"h":16},
	"rotated": false,
	"trimmed": false,
	"spriteSourceSize": {"x":0,"y":0,"w":16,"h":16},
	"sourceSize": {"w":16,"h":16},
	"anchor": {"x":0,"y":0}
},
"wasteland.png":
{
	"frame": {"x":125,"y":47,"w":16,"h":17},
	"rotated": false,
	"trimmed": true,
	"spriteSourceSize": {"x":0,"y":15,"w":16,"h":17},
	"sourceSize": {"w":16,"h":32},
	"anchor": {"x":0,"y":0.5}
},
"wood-00.png":
{
	"frame": {"x":486,"y":109,"w":16,"h":15},
	"rotated": true,
	"trimmed": true,
	"spriteSourceSize": {"x":0,"y":1,"w":16,"h":15},
	"sourceSize": {"w":16,"h":16},
	"anchor": {"x":0,"y":0}
},
"wood-01.png":
{
	"frame": {"x":451,"y":109,"w":16,"h":16},
	"rotated": false,
	"trimmed": false,
	"spriteSourceSize": {"x":0,"y":0,"w":16,"h":16},
	"sourceSize": {"w":16,"h":16},
	"anchor": {"x":0,"y":0}
},
"wood-10.png":
{
	"frame": {"x":469,"y":91,"w":16,"h":16},
	"rotated": false,
	"trimmed": false,
	"spriteSourceSize": {"x":0,"y":0,"w":16,"h":16},
	"sourceSize": {"w":16,"h":16},
	"anchor": {"x":0,"y":0}
},
"wood-11.png":
{
	"frame": {"x":557,"y":107,"w":16,"h":14},
	"rotated": false,
	"trimmed": true,
	"spriteSourceSize": {"x":0,"y":2,"w":16,"h":14},
	"sourceSize": {"w":16,"h":16},
	"anchor": {"x":0,"y":0}
},
"wood.png":
{
	"frame": {"x":143,"y":46,"w":16,"h":17},
	"rotated": false,
	"trimmed": true,
	"spriteSourceSize": {"x":0,"y":15,"w":16,"h":17},
	"sourceSize": {"w":16,"h":32},
	"anchor": {"x":0,"y":0.5}
}},
"animations": {
	"fire": ["fire-0.png","fire-1.png","fire-2.png","fire-3.png","fire-4.png","fire-5.png"],
	"meteor-0000": ["meteor-0000.png"],
	"meteor-0001": ["meteor-1-0001.png", "meteor-2-0001.png", "meteor-3-0001.png"],
	"meteor-0010": ["meteor-1-0010.png", "meteor-2-0010.png", "meteor-3-0010.png"],
	"meteor-0011": ["meteor-1-0011.png", "meteor-2-0011.png", "meteor-3-0011.png"],
	"meteor-0100": ["meteor-1-0100.png", "meteor-2-0100.png", "meteor-3-0100.png"],
	"meteor-0101": ["meteor-1-0101.png", "meteor-2-0101.png", "meteor-3-0101.png"],
	"meteor-0110": ["meteor-1-0110.png", "meteor-2-0110.png", "meteor-3-0110.png"],
	"meteor-0111": ["meteor-1-0111.png", "meteor-2-0111.png", "meteor-3-0111.png"],
	"plasma-0000": ["plasma-1-0000.png", "plasma-2-0000.png", "plasma-3-0000.png"],
	"plasma-0001": ["plasma-1-0001.png", "plasma-2-0001.png", "plasma-3-0001.png"],
	"plasma-0010": ["plasma-1-0010.png", "plasma-2-0010.png", "plasma-3-0010.png"],
	"plasma-0011": ["plasma-1-0011.png", "plasma-2-0011.png", "plasma-3-0011.png"],
	"plasma-0100": ["plasma-1-0100.png", "plasma-2-0100.png", "plasma-3-0100.png"],
	"plasma-0101": ["plasma-1-0101.png", "plasma-2-0101.png", "plasma-3-0101.png"],
	"plasma-0110": ["plasma-1-0110.png", "plasma-2-0110.png", "plasma-3-0110.png"],
	"plasma-0111": ["plasma-1-0111.png", "plasma-2-0111.png", "plasma-3-0111.png"],
	"plasma-1000": ["plasma-1-1000.png", "plasma-2-1000.png", "plasma-3-1000.png"],
	"plasma-1001": ["plasma-1-1001.png", "plasma-2-1001.png", "plasma-3-1001.png"],
	"plasma-1010": ["plasma-1-1010.png", "plasma-2-1010.png", "plasma-3-1010.png"],
	"plasma-1011": ["plasma-1-1011.png", "plasma-2-1011.png", "plasma-3-1011.png"],
	"plasma-1100": ["plasma-1-1100.png", "plasma-2-1100.png", "plasma-3-1100.png"],
	"plasma-1101": ["plasma-1-1101.png", "plasma-2-1101.png", "plasma-3-1101.png"],
	"plasma-1110": ["plasma-1-1110.png", "plasma-2-1110.png", "plasma-3-1110.png"],
	"plasma-1111": ["plasma-1-1111.png", "plasma-2-1111.png", "plasma-3-1111.png"],
	"rough": ["rough-0.png","rough-1.png","rough-2.png","rough-3.png","rough-4.png"],
	"sea": ["sea-0.png","sea-1.png","sea-2.png","sea-3.png","sea-4.png","sea-3.png","sea-2.png","sea-1.png"],
	"silo": ["silo-1.png","silo-2.png"]
},
"meta": {
	"app": "https://www.codeandweb.com/texturepacker",
	"version": "1.0",
	"image": "normal-map-tiles-sm.png",
	"format": "RGBA8888",
	"size": {"w":825,"h":126},
	"scale": "1",
	"smartupdate": "$TexturePacker:SmartUpdate:6c92697fdb0d63683f733e190a674a19:3119482b080e20f2ee91ea92dad3b931:0a63ece66da2861d7b2a5e79a1044014$"
}
}
